{
    "charid": "char_349_chiave",
    "nameid": "chiave",
    "names": {
        "en": "Chiave",
        "jp": "キアーベ",
        "kr": "키아베",
        "cn": "贾维"
    },
    "voices": [
        {
            "id": "char_349_chiave_CN_001",
            "title": {
                "en": "Appointed as Assistant",
                "jp": "秘書任命",
                "kr": "어시스턴트 임명",
                "cn": "任命助理"
            },
            "text": {
                "en": "Ehi, Doctor, got anything fun to do?",
                "jp": "おいドクター、なんか面白いことねぇの？",
                "kr": "야, 박사. 뭐 재밌는 거 없어?",
                "cn": "喂，博士，有没有什么好玩的事情？"
            },
            "asset": "char_349_chiave/CN_001"
        },
        {
            "id": "char_349_chiave_CN_002",
            "title": {
                "en": "Talk 1",
                "jp": "会話1",
                "kr": "대화 1",
                "cn": "交谈1"
            },
            "text": {
                "en": "Tsk, goddamn peppers... I gotta find a way to make them disappear from the canteen forever.",
                "jp": "チッ、ピーマンってモンを食堂から永遠に消し去る方法、なんかねぇのかな。",
                "kr": "칫, 피망이란 걸 식당에서 영원히 없애버릴 방법 같은 거, 어디 없을까.",
                "cn": "啧，得想个办法让食堂的青椒永远消失。"
            },
            "asset": "char_349_chiave/CN_002"
        },
        {
            "id": "char_349_chiave_CN_003",
            "title": {
                "en": "Talk 2",
                "jp": "会話2",
                "kr": "대화 2",
                "cn": "交谈2"
            },
            "text": {
                "en": "I heard Yanese got some old sayings similar to 'Catch the moment'. Heh, the line I like. Don't you think it suits me very well? The future? Meh, I'll let Aosta chew on those sorts of things.",
                "jp": "炎国には「今を楽しめ」ってコトワザがあるんだ。ハッ、俺様にピッタリだと思わねぇか？……将来？んなモンはアオスタの奴に任せときゃいいんだって。",
                "kr": "염국엔 '지금을 즐겨라'라는 속담이 있지. 하! 이 몸한테 딱 맞는 말 같지 않아? ……미래? 그딴 건 아오스타 한테 맡겨두면 된다니까.",
                "cn": "炎国有一句谚语，叫——“及时行乐”，嘿，这句话很适合小爷我。未来？这种东西让奥斯塔去想就好了。"
            },
            "asset": "char_349_chiave/CN_003"
        },
        {
            "id": "char_349_chiave_CN_004",
            "title": {
                "en": "Talk 3",
                "jp": "会話3",
                "kr": "대화 3",
                "cn": "交谈3"
            },
            "text": {
                "en": "Oi, Doctor, don't just sit there all day. Why don't we have some fun, like… remodeling your whole office?",
                "jp": "おいドクター、んなとこで座りっぱなしじゃつまんねぇだろ。ちょっとおもしれぇことでもしようぜ。この執務室を改造してみるとかさ、どうだ？",
                "kr": "야, 박사. 그런 곳에 계속 앉아있으면 안 따분해? 뭐 재밌는 거라도 찾아보자. 여기 집무실을 개조해 보는 건 어때?",
                "cn": "喂，博士，别老坐那儿啊，我们来找点乐子吧，比如把这间办公室改造一下怎么样？"
            },
            "asset": "char_349_chiave/CN_004"
        },
        {
            "id": "char_349_chiave_CN_005",
            "title": {
                "en": "Talk after Promotion 1",
                "jp": "昇進後会話1",
                "kr": "1차 정예화 후 대화",
                "cn": "晋升后交谈1"
            },
            "text": {
                "en": "Aosta once said I wouldn't live long like this. At the time, I told him, what's the point of long life if I can't do what I want?",
                "jp": "アオスタに言われたことがあんだよ、「お前そんなんじゃ長生きできないぞ」って。「そんなんじゃないと、長生きしてもつまんねぇだけだ」って言い返してやったよ。",
                "kr": "아오스타가 전에 그러더라고, “그러면 제 명에 못 산다”고. 그래서 내가 뭐라 그랬게?  “안 그러면 따분해 죽을 텐데 오래 살아봤자 뭐해!” 이렇게 받아쳐 줬지.",
                "cn": "奥斯塔以前跟我说，我这样活不久。我当时告诉他，如果我不这样，那活久了又有什么意思？"
            },
            "asset": "char_349_chiave/CN_005"
        },
        {
            "id": "char_349_chiave_CN_006",
            "title": {
                "en": "Talk after Promotion 2",
                "jp": "昇進後会話2",
                "kr": "2차 정예화 후 대화",
                "cn": "晋升后交谈2"
            },
            "text": {
                "en": "Fight for what you want, snatch what you like. I don't know the meaning of the word 'Surrender'!",
                "jp": "欲しいモンがあれば手を伸ばす、好きなモンがあれば奪い取る。俺様の辞書にゃ、「諦める」って言葉が存在しねぇんだよ！",
                "kr": "원하는 게 있으면 손을 뻗는다, 좋아하는 게 있으면 빼앗는다. 이 몸의 사전에는 '포기'라는 말이 없다고!",
                "cn": "想要的就去争，喜欢的就去抢，小爷我的字典里，从来没有“放弃”两个字！"
            },
            "asset": "char_349_chiave/CN_006"
        },
        {
            "id": "char_349_chiave_CN_007",
            "title": {
                "en": "Talk after Trust Increase 1",
                "jp": "信頼上昇後会話1",
                "kr": "신뢰도 상승 후 대화 1",
                "cn": "信赖提升后交谈1"
            },
            "text": {
                "en": "I think up what to do, Aosta thinks up how to do it, and Broca makes sure we get it done together. That's how we've always gotten by, and it's how we ended up here.",
                "jp": "俺が何をやるか考えて、アオスタがやり方を考えて、ブローカが一緒にやる。今までずっとこうしてやってきたんだ。",
                "kr": "내가 뭘 할지를 생각하고, 아오스타가 방법을 생각하고, 브로카가 그걸 또 같이하고. 우린 지금까지 계속 이렇게 해 왔어.",
                "cn": "我来想做什么，奥斯塔想怎么做，布洛卡就负责一起做，一直以来，我们都是这么过来的。"
            },
            "asset": "char_349_chiave/CN_007"
        },
        {
            "id": "char_349_chiave_CN_008",
            "title": {
                "en": "Talk after Trust Increase 2",
                "jp": "信頼上昇後会話2",
                "kr": "신뢰도 상승 후 대화 2",
                "cn": "信赖提升后交谈2"
            },
            "text": {
                "en": "Doctor, what are you doing all frowny-faced over there? If there's anything weighing on you, just lay it on me. I'm good at that sort of stuff.",
                "jp": "ドクター、そんな眉間にしわ寄せて何考えてんだ？悩みがあんなら言ってみろ、俺がなんとかしてやるよ。こういうのは俺得意だからな。",
                "kr": "박사, 뭔 생각을 하길래 그렇게 인상을 쓰고 있어? 고민이 있으면 말해 봐. 내가 어떻게든 해줄 테니까. 내가 또 이런 건 잘하거든.",
                "cn": "博士，皱着眉头想什么呢，有什么烦恼说给我听听，我来帮你出主意，这个我擅长。"
            },
            "asset": "char_349_chiave/CN_008"
        },
        {
            "id": "char_349_chiave_CN_009",
            "title": {
                "en": "Talk after Trust Increase 3",
                "jp": "信頼上昇後会話3",
                "kr": "신뢰도 상승 후 대화 3",
                "cn": "信赖提升后交谈3"
            },
            "text": {
                "en": "Say, Doctor, if someday you decide to quit running Rhodes Island, why not come along with us? Chiave doesn't take orders from anyone, but in your case, I'll make an exception.",
                "jp": "なぁドクター、いつかロドスのボスを辞めることになったら、俺らと一緒に来るか？俺様は誰にも頭を下げるつもりはねぇんだけど、お前になら従ってやってもいいと思ってな。",
                "kr": "야, 박사. 언제 로도스 아일랜드에서 보스 노릇 하는 거 그만두면 우리한테 올래? 난 누구한테도 머리 숙일 생각은 없지만, 너라면 따라줘도 괜찮을 거 같거든.",
                "cn": "我说，博士，哪天你要是不当罗德岛的头头了，来跟我们一起干怎么样？小爷我平时不服谁，但对你是服气的，我给你打下手也ok啊。"
            },
            "asset": "char_349_chiave/CN_009"
        },
        {
            "id": "char_349_chiave_CN_010",
            "title": {
                "en": "Idle",
                "jp": "放置",
                "kr": "방치",
                "cn": "闲置"
            },
            "text": {
                "en": "Ehi, Doctor... You fell asleep? Whatever, I'll be back later.",
                "jp": "おいドクター……なんだ寝てんのか。まぁ後でいいや。",
                "kr": "야, 박사…… 뭐야, 자고 있네. 뭐, 나중에 하지.",
                "cn": "喂，博士......怎么睡着了，算了，那等会儿再说。"
            },
            "asset": "char_349_chiave/CN_010"
        },
        {
            "id": "char_349_chiave_CN_011",
            "title": {
                "en": "Onboard",
                "jp": "入職会話",
                "kr": "오퍼레이터 입사",
                "cn": "干员报到"
            },
            "text": {
                "en": "Yo, are you the Doctor? Hello, and well met. The name's Chiave. Starting today, I'm your goon!",
                "jp": "おー、お前がドクターか？会えて嬉しいぜ。俺様はキアーべ、今日からお前の子分になってやるよ、よろしくな！",
                "kr": "오~ 네가 박사야? 만나서 반가워. 이 몸은 키아베, 오늘부터 네 부하가 되어 줄게. 잘 부탁해!",
                "cn": "嘿，你就是博士吧？你好你好，幸会幸会，小爷贾维，今天起就是你的手下了！"
            },
            "asset": "char_349_chiave/CN_011"
        },
        {
            "id": "char_349_chiave_CN_012",
            "title": {
                "en": "Watching Battle Record",
                "jp": "経験値上昇",
                "kr": "작전기록 학습",
                "cn": "观看作战记录"
            },
            "text": {
                "en": "Whoa-ho-ho... Hey Aosta, check this out! Give me a moment and I'll be even stronger than these guys!",
                "jp": "おいアオスタ、見ろよこれ、俺もいつかこんなすげぇ奴になってやる！",
                "kr": "야, 아오스타. 이리로 와봐, 봐봐 이거. 나도 언젠간 이 녀석처럼 굉장해질 거야!",
                "cn": "啧啧，奥斯塔，快过来瞧瞧，我有一天也要变得这么强！"
            },
            "asset": "char_349_chiave/CN_012"
        },
        {
            "id": "char_349_chiave_CN_013",
            "title": {
                "en": "Promotion 1",
                "jp": "昇進Ⅰ",
                "kr": "1차 정예화 (승진)",
                "cn": "精英化晋升1"
            },
            "text": {
                "en": "Huh? Promotion? What do you mean?",
                "jp": "んあ？昇進？なんじゃそりゃ？",
                "kr": "뭐? 승진? 뭔데, 그게?",
                "cn": "啊？升职？那是什么？"
            },
            "asset": "char_349_chiave/CN_013"
        },
        {
            "id": "char_349_chiave_CN_014",
            "title": {
                "en": "Promotion 2",
                "jp": "昇進Ⅱ",
                "kr": "2차 정예화 (승진)",
                "cn": "精英化晋升2"
            },
            "text": {
                "en": "Incredible. There are just too many interesting people here at Rhodes Island. How am I supposed to just stay in my seat? I've gotta get stronger and stronger!",
                "jp": "やべぇ、ロドスにおもしれぇ奴がこんなにいるとはな！じっとしてらんねぇな、俺ももっと強くならねぇと！",
                "kr": "쩌는데! 로도스 아일랜드에 재밌는 녀석이 이렇게나 많이 있을 줄은 몰랐어! 나도 가만히 있을 수 없지. 더 강해져야겠어!",
                "cn": "不得了啊，罗德岛里有趣的家伙也太多了，这让我怎么坐得住，要变得更强，更强才行！"
            },
            "asset": "char_349_chiave/CN_014"
        },
        {
            "id": "char_349_chiave_CN_017",
            "title": {
                "en": "Added to Squad",
                "jp": "編成",
                "kr": "팀 배치",
                "cn": "编入队伍"
            },
            "text": {
                "en": "Ha, here we go!",
                "jp": "よし、行くぜ！",
                "kr": "좋아, 가자!",
                "cn": "嘿，走着！"
            },
            "asset": "char_349_chiave/CN_017"
        },
        {
            "id": "char_349_chiave_CN_018",
            "title": {
                "en": "Appointed as Squad Leader",
                "jp": "隊長任命",
                "kr": "팀장 임명",
                "cn": "任命队长"
            },
            "text": {
                "en": "Listen up, everyone, I have a plan!",
                "jp": "なぁお前ら、俺にちょっと考えがあんだ。",
                "kr": "얘들아 잠깐만. 나한테 좋은 생각이 있거든.",
                "cn": "听我说，各位，我有个计划！"
            },
            "asset": "char_349_chiave/CN_018"
        },
        {
            "id": "char_349_chiave_CN_019",
            "title": {
                "en": "Depart",
                "jp": "作戦準備",
                "kr": "작전 출발",
                "cn": "行动出发"
            },
            "text": {
                "en": "Haha, let's go make some noise!",
                "jp": "ハハッ、ド派手にやってやろうぜ！",
                "kr": "하하! 화려하게 한번 날뛰어 보자고!",
                "cn": "哈哈，让我们干一票大的！"
            },
            "asset": "char_349_chiave/CN_019"
        },
        {
            "id": "char_349_chiave_CN_020",
            "title": {
                "en": "Begin Operation",
                "jp": "戦闘開始",
                "kr": "작전 개시",
                "cn": "行动开始"
            },
            "text": {
                "en": "Just gotta knock 'em all down, right?",
                "jp": "全員ぶっ潰せばいいんだな？",
                "kr": "전부 쳐부숴 버리면 되는 거지?",
                "cn": "把他们全都干趴下就行了吧？"
            },
            "asset": "char_349_chiave/CN_020"
        },
        {
            "id": "char_349_chiave_CN_021",
            "title": {
                "en": "Selecting Operator 1",
                "jp": "選択時1",
                "kr": "오퍼레이터 선택 1",
                "cn": "选中干员1"
            },
            "text": {
                "en": "Still not my turn yet?",
                "jp": "俺様の出番はまだか？",
                "kr": "내 차례는 아직이야?",
                "cn": "还没轮到小爷？"
            },
            "asset": "char_349_chiave/CN_021"
        },
        {
            "id": "char_349_chiave_CN_022",
            "title": {
                "en": "Selecting Operator 2",
                "jp": "選択時2",
                "kr": "오퍼레이터 선택 2",
                "cn": "选中干员2"
            },
            "text": {
                "en": "C'mon, don't make me yawn.",
                "jp": "あんま退屈させんなよ。",
                "kr": "너무 지루하게 하지 말라고!",
                "cn": "别让我太无聊啊。"
            },
            "asset": "char_349_chiave/CN_022"
        },
        {
            "id": "char_349_chiave_CN_023",
            "title": {
                "en": "Deployment 1",
                "jp": "配置1",
                "kr": "배치 1",
                "cn": "部署1"
            },
            "text": {
                "en": "I can't wait any longer!",
                "jp": "もう待ちくたびれたぜ！",
                "kr": "기다리다 심심해 죽는 줄 알았네!",
                "cn": "我已经等不及了！"
            },
            "asset": "char_349_chiave/CN_023"
        },
        {
            "id": "char_349_chiave_CN_024",
            "title": {
                "en": "Deployment 2",
                "jp": "配置2",
                "kr": "배치 2",
                "cn": "部署2"
            },
            "text": {
                "en": "Haha, I'm gonna end you all!",
                "jp": "ハハッ、お前らはもう終わりだ！",
                "kr": "하하! 너희는 이제 끝이다!",
                "cn": "哈哈，你们死定了！"
            },
            "asset": "char_349_chiave/CN_024"
        },
        {
            "id": "char_349_chiave_CN_025",
            "title": {
                "en": "In Battle 1",
                "jp": "作戦中1",
                "kr": "작전 중 1",
                "cn": "作战中1"
            },
            "text": {
                "en": "Take this!",
                "jp": "これでも喰らえ！",
                "kr": "이거나 먹어라!",
                "cn": "尝尝这个！"
            },
            "asset": "char_349_chiave/CN_025"
        },
        {
            "id": "char_349_chiave_CN_026",
            "title": {
                "en": "In Battle 2",
                "jp": "作戦中2",
                "kr": "작전 중 2",
                "cn": "作战中2"
            },
            "text": {
                "en": "Hey! Why are you running?!",
                "jp": "おい、逃げんな！",
                "kr": "이 자식이 어딜 도망가!",
                "cn": "喂，别跑啊！"
            },
            "asset": "char_349_chiave/CN_026"
        },
        {
            "id": "char_349_chiave_CN_027",
            "title": {
                "en": "In Battle 3",
                "jp": "作戦中3",
                "kr": "작전 중 3",
                "cn": "作战中3"
            },
            "text": {
                "en": "Yeah, yeah, you've all done a great JOB!",
                "jp": "へいへい、お前らもよく頑張りました、っと。",
                "kr": "늬예 늬예~ 너희도 참 잘하셨습니…… 다!",
                "cn": "好了好了，你们已经很努力了。"
            },
            "asset": "char_349_chiave/CN_027"
        },
        {
            "id": "char_349_chiave_CN_028",
            "title": {
                "en": "In Battle 4",
                "jp": "作戦中4",
                "kr": "작전 중 4",
                "cn": "作战中4"
            },
            "text": {
                "en": "I'm on FIRE!",
                "jp": "ワクワクしてきたぜ！",
                "kr": "슬슬 흥분되는데!",
                "cn": "我兴奋起来了！"
            },
            "asset": "char_349_chiave/CN_028"
        },
        {
            "id": "char_349_chiave_CN_029",
            "title": {
                "en": "4-star Result",
                "jp": "高難度作戦クリア",
                "kr": "고난이도 작전 종료",
                "cn": "完成高难行动"
            },
            "text": {
                "en": "Hah, now this is the fun stuff!",
                "jp": "ハッ、刺激のある任務はこうでなきゃな！",
                "kr": "하! 자극적인 임무는 이런 맛이 좀 있어야지!",
                "cn": "哈，就是要这样的任务才刺激啊！"
            },
            "asset": "char_349_chiave/CN_029"
        },
        {
            "id": "char_349_chiave_CN_030",
            "title": {
                "en": "3-star Result",
                "jp": "★3で戦闘終了",
                "kr": "3★ 작전 종료",
                "cn": "3星结束行动"
            },
            "text": {
                "en": "Ah. Where's the challenge in that, Doctor?",
                "jp": "チェー、こんくらいじゃ話にもならねぇな、ドクター。",
                "kr": "쳇, 이 정도면 이야깃거리도 안 되잖아, 박사.",
                "cn": "啧啧，没什么挑战啊，博士。"
            },
            "asset": "char_349_chiave/CN_030"
        },
        {
            "id": "char_349_chiave_CN_031",
            "title": {
                "en": "Sub 3-star Result",
                "jp": "★2以下戦闘終了",
                "kr": "비 3★ 작전 종료",
                "cn": "非3星结束行动"
            },
            "text": {
                "en": "Huh? I left a few? Never even saw 'em.",
                "jp": "んあ？何人か逃がした？そりゃ気付かなかったな。",
                "kr": "어? 몇 명 놓쳤다고? 그건 몰랐네.",
                "cn": "啊？溜了几个？我都没发现。"
            },
            "asset": "char_349_chiave/CN_031"
        },
        {
            "id": "char_349_chiave_CN_032",
            "title": {
                "en": "Operation Failure",
                "jp": "作戦失敗",
                "kr": "작전 실패",
                "cn": "行动失败"
            },
            "text": {
                "en": "Shit, for real?!",
                "jp": "che cazzo uomo！",
                "kr": "Che cazzo uomo!",
                "cn": "Che cazzo uomo！"
            },
            "asset": "char_349_chiave/CN_032"
        },
        {
            "id": "char_349_chiave_CN_033",
            "title": {
                "en": "Assigned to Facility",
                "jp": "基地配属",
                "kr": "시설에 배치",
                "cn": "进驻设施"
            },
            "text": {
                "en": "ello, bruthas and sistahs!",
                "jp": "よお、兄ちゃんたち姉ちゃんたち元気か～？",
                "kr": "여어~ 형님들 누님들, 잘 있었지~?",
                "cn": "大哥大姐们好啊！"
            },
            "asset": "char_349_chiave/CN_033"
        },
        {
            "id": "char_349_chiave_CN_034",
            "title": {
                "en": "Tap",
                "jp": "タッチ1",
                "kr": "터치",
                "cn": "戳一下"
            },
            "text": {
                "en": "What is it?",
                "jp": "なんだ？",
                "kr": "왜?",
                "cn": "干嘛？"
            },
            "asset": "char_349_chiave/CN_034"
        },
        {
            "id": "char_349_chiave_CN_036",
            "title": {
                "en": "Trust Tap",
                "jp": "信頼タッチ",
                "kr": "신뢰도 터치",
                "cn": "信赖触摸"
            },
            "text": {
                "en": "Yo, Doctor, you're in a pretty good mood.",
                "jp": "ハッ、ドクター、機嫌良さそうじゃねぇか。",
                "kr": "하! 박사, 기분이 좋아 보이네.",
                "cn": "嘿，博士，心情不错啊。"
            },
            "asset": "char_349_chiave/CN_036"
        },
        {
            "id": "char_349_chiave_CN_037",
            "title": {
                "en": "Title",
                "jp": "タイトルコール",
                "kr": "타이틀",
                "cn": "标题"
            },
            "text": {
                "en": "Arknights.",
                "jp": "アークナイツ。",
                "kr": "명일방주.",
                "cn": "明日方舟。"
            },
            "asset": "char_349_chiave/CN_037"
        },
        {
            "id": "char_349_chiave_CN_038",
            "title": {
                "en": "New Year's blessing",
                "jp": "新年",
                "kr": "새해",
                "cn": "新年祝福"
            },
            "text": {
                "en": "Doctor! Aosta, Broca, and I have a new New Year's plan. Heh heh, once I tell you, you're in on the game. We're going to swap out all the chocolate sauce in the canteen for Siracusan meat sauce, then— Huh? Doctor, where are you going?! Don't you tell Dr. Kal'tsit!",
                "jp": "ドクター！アオスタとブローカと一緒に元日の計画を立てたんだが知りてぇか？ヘヘッ、聞いた上で参加しねぇってのはナシだぜ。いいか、まず食堂のチョコレートソースを全部シラクーザ風ミートソースに取っ替えて、それから――おいドクター、逃げんな！ケルシー先生にはチクんなよ！",
                "kr": "박사! 아오스타, 브로카랑 새해 계획을 세웠는데, 헤헤, 듣고 싶어? 근데 이걸 듣고 나면 박사도 우리 계획에 참여해야만 해. 자, 그럼 잘 들어. 먼저 식당의 초콜릿 시럽을 전부 시라쿠사 미트소스로 바꾼 다음…… 어이, 박사. 거기 서! 닥터 켈시한테 말하면 안 된다고!",
                "cn": "博士！我和奥斯塔、布洛卡有一个新年计划，哼哼，告诉你的话，你可就必须加入了。我们打算偷偷把食堂的巧克力酱全部换成叙拉古肉酱，然后——欸，博士，你别走啊！别告诉凯尔希医生啊！"
            },
            "asset": "char_349_chiave/CN_038"
        },
        {
            "id": "char_349_chiave_CN_042",
            "title": {
                "en": "Greeting",
                "jp": "挨拶",
                "kr": "인사",
                "cn": "问候"
            },
            "text": {
                "en": "Ehi Doc, did you have a good meal?",
                "jp": "ドクター、メシはもう食ったか？",
                "kr": "박사, 밥 먹었어?",
                "cn": "博士，吃过没？"
            },
            "asset": "char_349_chiave/CN_042"
        },
        {
            "id": "char_349_chiave_CN_044",
            "title": {
                "en": "Anniversary Celebration",
                "jp": "周年",
                "kr": "애니버서리",
                "cn": "周年庆典"
            },
            "text": {
                "en": "Rhodes Island's got all these heavies, plus smart people like you. One day, someday, I'm gonna do something big that'll rock the whole world! At the very least, I'll do it before I die! Uh, I should try to stay alive...? I guess you're right, haha…",
                "jp": "ロドスにゃすげー奴が山ほどいるし、ドクターみてぇに頭がキレる奴もいるだろ。俺様だっていつか、いつか絶対一発ドデケェことをやってみせるぜ！遅くとも死んじまう前にな！あ？まずは死なないことを考えろ？それもそうだな、ハハッ……",
                "kr": "로도스 아일랜드에는 대단한 사람들이 정말 많아. 박사처럼 똑똑한 사람도 있고. 나도 언젠가는, 꼭 이 대지를 들었다 놓는 일을 벌일 거야! 적어도 내가 죽기 전에는 반드시! 윽, 일단 잘 살아남기나 하라고? 그것도 그렇네, 하하……",
                "cn": "罗德岛有这么多厉害的人，还有像博士这样聪明的人。总有一天，总有一天我也要干一番惊天动地的大事！至少在我死之前要做到！呃——还是先好好活着？说的也是啊哈哈......"
            },
            "asset": "char_349_chiave/CN_044"
        }
    ],
    "actors": {
        "en": {
            "native": "Jacopo Calatroni",
            "global": "Jacopo Calatroni"
        },
        "cn": {
            "native": "张桐铭",
            "global": "Tongming Zhang"
        },
        "jp": {
            "native": "羽多野渉",
            "global": "Wataru Hatano"
        },
        "kr": {
            "native": "김지율",
            "global": "Kim Ji-yul"
        }
    },
    "availability": [
        "en",
        "cn",
        "jp",
        "kr"
    ]
}