{
    "charid": "char_214_kafka",
    "nameid": "kafka",
    "names": {
        "en": "Kafka",
        "jp": "カフカ",
        "kr": "카프카",
        "cn": "卡夫卡"
    },
    "voices": [
        {
            "id": "char_214_kafka_CN_001",
            "title": {
                "en": "Appointed as Assistant",
                "jp": "秘書任命",
                "kr": "어시스턴트 임명",
                "cn": "任命助理"
            },
            "text": {
                "en": "You give Kafka the work that needs doing, Doctor, and then I pass it all on... okay! This's just like how underground gofering goes!",
                "jp": "ドクターがそれぞれのやるべき仕事をカフカに伝えて、それからカフカがみんなに伝える……オッケー。こんなの、闇仲介の仕事と一緒じゃん！",
                "kr": "박사가 각자 해야 할 일을 카프카에게 전하고, 그걸 카프카가 모두에게 전한다…… 오케이~ 이런 거, 브로커 일이랑 똑같네 뭐~!",
                "cn": "博士把要做的工作告诉卡夫卡，再由卡夫卡来转达......明白了。这不就是地下中介的标准工作流程吗！"
            },
            "asset": "char_214_kafka/CN_001"
        },
        {
            "id": "char_214_kafka_CN_002",
            "title": {
                "en": "Talk 1",
                "jp": "会話1",
                "kr": "대화 1",
                "cn": "交谈1"
            },
            "text": {
                "en": "Seeing as you're my friend now, Doctor, you can ask me for anything. Oh, but, apart from lending you my shears.",
                "jp": "ドクターはもうカフカの友達なんだから、やってほしいことは何でも言って！あっ、ハサミの貸し出し以外でね。",
                "kr": "박사는 이제 카프카랑 친구니까, 원하는 게 있으면 뭐든지 말해! 아, 가위 빌려달라는 것만 빼고.",
                "cn": "既然博士已经成为卡夫卡的朋友了，那么除了剪刀不能外借，其他的请求尽管提就可以了！"
            },
            "asset": "char_214_kafka/CN_002"
        },
        {
            "id": "char_214_kafka_CN_003",
            "title": {
                "en": "Talk 2",
                "jp": "会話2",
                "kr": "대화 2",
                "cn": "交谈2"
            },
            "text": {
                "en": "Rhodes Island's fulla all sortsa people I never met before. Everywhere I go, I sees what I wants. Hm? You're wonderin' WHAT it is I want? That's a secret, y'know. Secret.",
                "jp": "ロドスには知らない人ばっかり、カフカの欲しいものだらけだ！ん？何が欲しいって？それはー、秘密だよ。ひー、みー、つー。",
                "kr": "로도스 아일랜드는 모르는 사람이 잔뜩~ 카프카가 원하는 걸로 가득해! 응? 원하는 게 뭐냐고? 그건~ 비밀이야. 비. 밀.",
                "cn": "罗德岛有好多陌生的人，到处都是卡夫卡想要的东西。嗯？博士问我想要什么？这可是秘密啊。秘、密。"
            },
            "asset": "char_214_kafka/CN_003"
        },
        {
            "id": "char_214_kafka_CN_004",
            "title": {
                "en": "Talk 3",
                "jp": "会話3",
                "kr": "대화 3",
                "cn": "交谈3"
            },
            "text": {
                "en": "Hmm... still can't read your eyes. They're calm as a lake... But there'll come a day when I get your number, Doctor, just you wait!",
                "jp": "むむ……ドクターの目からは相変わらず何も読み取れないなー。波一つ立たない湖みたい……でもいつか絶対、ドクターの尻尾を掴んでやるぞ！",
                "kr": "으음…… 박사의 눈에서는 여전히 아무것도 읽을 수가 없네. 파도 한 점 없는 호수 같아…… 그래도 두고 봐! 언젠가 반드시! 박사의 꼬리를 잡고 말 테니까!",
                "cn": "嗯......博士的眼神还是一如既往地平静如水。完全看不透啊......不过总有一天，卡夫卡会抓住博士的破绽的！"
            },
            "asset": "char_214_kafka/CN_004"
        },
        {
            "id": "char_214_kafka_CN_005",
            "title": {
                "en": "Talk after Promotion 1",
                "jp": "昇進後会話1",
                "kr": "1차 정예화 후 대화",
                "cn": "晋升后交谈1"
            },
            "text": {
                "en": "Doctor, Silence kicked me out againnn! Hard times for a Kafka, sob, sob... huh? I started it by messing up her experiment? Aw, nerts, Silence got to you first... eh-hem, well, good talking, I'm just gonna mosey on out now!",
                "jp": "ドクター、カフカまたサイレンスに追い出されちゃったよ。もう悲しくて涙が止まらないよしくしく……え？カフカが実験をダメにしたのが悪いって聞いてる？むむ、先を越されたか……コホン、じゃあカフカは退散するわ～。",
                "kr": "박사, 카프카 또 사일런스한테 쫓겨났어. 너무 슬퍼서 눈물이 멈추지 않아, 흐흑…… 응? 카프카가 실험을 망친 게 잘못이라 들었다고? 쳇…… 선수를 빼앗겼나…… 크흠, 그럼 카프카는 이만 철수할게~",
                "cn": "博士，赫默又把我赶出来了，我好难过哦，呜呜呜......诶？是我先把她的实验搞砸了？唔，居然被赫默抢先一步......咳咳，那我先走了！"
            },
            "asset": "char_214_kafka/CN_005"
        },
        {
            "id": "char_214_kafka_CN_006",
            "title": {
                "en": "Talk after Promotion 2",
                "jp": "昇進後会話2",
                "kr": "2차 정예화 후 대화",
                "cn": "晋升后交谈2"
            },
            "text": {
                "en": "Well, until I can get what I want, I guess I'll lend you a hand. Just lending it, though, okay?",
                "jp": "まぁ、カフカの欲しいものが手に入るまでの間、とりあえず力を貸してあげるよ。貸してるだけだからね。",
                "kr": "뭐, 카프카가 원하는 걸 손에 넣을 때까지, 일단은 힘을 빌려줄게. 빌려주기만 하는 거다?",
                "cn": "好吧，那在我得到想要的东西之前，就暂且把我的力量先借给你吧。不过只是借哦。"
            },
            "asset": "char_214_kafka/CN_006"
        },
        {
            "id": "char_214_kafka_CN_007",
            "title": {
                "en": "Talk after Trust Increase 1",
                "jp": "信頼上昇後会話1",
                "kr": "신뢰도 상승 후 대화 1",
                "cn": "信赖提升后交谈1"
            },
            "text": {
                "en": "Story goes, I used to live in a real maaad kinda city, dealing with bad people alla the day. But then I came landship-side, and everyone's been some kinda nice with me, even givin' me snacks and all! Mm-hm, and that's why I like it here at Rhodes Island!",
                "jp": "カフカは昔、とってもやばいところに住んでたの。毎日のように悪い人に付き合ってたよ。でもここに来てから、みんなカフカに親切だし、美味しいお菓子もたくさんくれるし。だからカフカはロドスが好きだよー！",
                "kr": "카프카는 전에 엄~청 위험한 곳에서 살았었어. 매일같이 나쁜 사람들이랑 어울려 다녔지. 근데 여기 오고 나니까, 모두 카프카에게 친절하게 대해주고, 맛있는 과자도 많이 줘. 그래서, 카프카는 로도스 아일랜드가 좋아~!",
                "cn": "卡夫卡以前住在很糟糕的地方，每天几乎都在和坏人打交道。来到这里以后，大家对卡夫卡都很友善，还给我很多好吃的零食。嗯，所以卡夫卡还是很喜欢罗德岛的！"
            },
            "asset": "char_214_kafka/CN_007"
        },
        {
            "id": "char_214_kafka_CN_008",
            "title": {
                "en": "Talk after Trust Increase 2",
                "jp": "信頼上昇後会話2",
                "kr": "신뢰도 상승 후 대화 2",
                "cn": "信赖提升后交谈2"
            },
            "text": {
                "en": "...Y'know the secrets everyone tries their best to hide? They're like monsters, hidden in the dead shadows, waitin' for their chance. Beautiful... and dangerous. That's exactly why I do my darndest to collect them! Doctor, don't you got anything for my hoard?",
                "jp": "……みんな必死に隠してる秘密は、物陰に潜んで機を伺う怪物のように危険で美しい。だからカフカは、こうやって頑張ってコレクションにしてるの。ドクターにも何かカフカのコレクションに入るようなものはない？",
                "kr": "……다들 필사적으로 숨기는 비밀은 그늘에 숨어서 기회를 엿보는 괴물처럼 위험하고 아름다워. 그래서 카프카는, 이렇게 열심히 컬렉션으로 만들고 있어. 박사는 뭐, 카프카의 컬렉션에 넣을 만한 거 없어?",
                "cn": "......大家竭力隐藏的秘密，就像静静潜伏在阴影里，伺机而动的怪物一样美丽而危险。所以我才要努力把它们变成我的收藏品啊。博士，你有什么能够让我收藏的东西吗？"
            },
            "asset": "char_214_kafka/CN_008"
        },
        {
            "id": "char_214_kafka_CN_009",
            "title": {
                "en": "Talk after Trust Increase 3",
                "jp": "信頼上昇後会話3",
                "kr": "신뢰도 상승 후 대화 3",
                "cn": "信赖提升后交谈3"
            },
            "text": {
                "en": "Doctor, if you've ever got a problem, we can always call my 'friends' from Columbia in to help. Though you don't really gotta. One Kafka'll sort out all your troubles head to tail!",
                "jp": "ドクター、もし何か困り事があれば、クルビアにいるカフカの「お友達」を呼べばいいよ……まぁそこまでする必要はないけどね。どんな難題でも、カフカ一人でぜーんぶ片付けちゃうから。",
                "kr": "박사, 혹시 곤란한 일이 있으면 컬럼비아에 있는 카프카의 '친구'를 부르면 돼~ 뭐, 사실 그렇게까지 할 필요는 없지만. 어떤 난관이라도 카프카 혼자서 다~ 정리할 수 있으니까.",
                "cn": "博士如果遇到难处，就把我在哥伦比亚的“朋友们”叫来帮忙吧......不过没什么必要啦。卡夫卡一个人就能把任何困难统统解决掉的。"
            },
            "asset": "char_214_kafka/CN_009"
        },
        {
            "id": "char_214_kafka_CN_010",
            "title": {
                "en": "Idle",
                "jp": "放置",
                "kr": "방치",
                "cn": "闲置"
            },
            "text": {
                "en": "Bet you think I'm goofing off right now, Doctor. But I ain't.",
                "jp": "ドクター、きっとこの隙にカフカがサボってると思ってるでしょ。でも違うんだよな～。",
                "kr": "박사, 분명히 이 틈에 카프카가 농땡이 부리고 있을 거라고 생각했지? 근데 틀렸지롱~",
                "cn": "博士一定是觉得卡夫卡在偷懒吧。但是并没有哦~"
            },
            "asset": "char_214_kafka/CN_010"
        },
        {
            "id": "char_214_kafka_CN_011",
            "title": {
                "en": "Onboard",
                "jp": "入職会話",
                "kr": "오퍼레이터 입사",
                "cn": "干员报到"
            },
            "text": {
                "en": "Whatcha need me for...? Hey, hey, wait, no bean-spilling, not in front of everybody! Just treat me like a normal gardener, okay?",
                "jp": "カフカに何の用……ちょっと、こんな大勢の前で言っちゃダメでしょ、普通の園芸師として扱ってよ。",
                "kr": "카프카한테 무슨 일…… 잠깐, 사람들 이렇게 많을 땐 그렇게 말하지 말라니까?! 내가 전에 평범한 원예사 취급해달라 그랬잖아!",
                "cn": "找卡夫卡有什么事吗......喂，不要当着这么多人说出来啊。当我是个普通的园艺师就好啦。"
            },
            "asset": "char_214_kafka/CN_011"
        },
        {
            "id": "char_214_kafka_CN_012",
            "title": {
                "en": "Watching Battle Record",
                "jp": "経験値上昇",
                "kr": "작전기록 학습",
                "cn": "观看作战记录"
            },
            "text": {
                "en": "Just gotta figure what they're aiming for, and I can draw up some counterplans. C'mon, ain't I a wiz?",
                "jp": "相手の目的さえ読み取れば、対策も立てられるでしょ。カフカってば超頭良いじゃん！",
                "kr": "상대방의 목적만 파악하면 대책도 세울 수 있겠지? 카프카는 정말 머리가 좋다니까!",
                "cn": "只要猜出对方的目的，就能制定出来对策了吧。卡夫卡是不是很聪明？"
            },
            "asset": "char_214_kafka/CN_012"
        },
        {
            "id": "char_214_kafka_CN_013",
            "title": {
                "en": "Promotion 1",
                "jp": "昇進Ⅰ",
                "kr": "1차 정예화 (승진)",
                "cn": "精英化晋升1"
            },
            "text": {
                "en": "Seeing as you really need my power, Doctor, just c'mon and say it. Be like Kafka here, all serious and open, yeah?",
                "jp": "ドクター、どーしてもカフカの力が欲しいなら、はっきり言ってよ。カフカみたいに真面目で素直でいいんじゃない？",
                "kr": "박사, 그렇~게까지 카프카의 힘이 필요하면, 그냥 확실히 말해달라구~ 카프카처럼 진지하고 솔직하면 어디 좀 좋아?",
                "cn": "既然博士非常需要卡夫卡的力量的话，直说就可以了。像卡夫卡一样认真又坦率不是很好吗？"
            },
            "asset": "char_214_kafka/CN_013"
        },
        {
            "id": "char_214_kafka_CN_014",
            "title": {
                "en": "Promotion 2",
                "jp": "昇進Ⅱ",
                "kr": "2차 정예화 (승진)",
                "cn": "精英化晋升2"
            },
            "text": {
                "en": "Gardenin' or fightin', I didn't start doing either for compliments. But having my own efforts get noticed by you and the rest, well, that makes a Kafka real happy.",
                "jp": "園芸も戦いも、褒められるために始めたわけじゃないよ。でもドクターやみんなにカフカの努力を認めてもらえるのって、やっぱり嬉しいな！",
                "kr": "원예도 전투도, 칭찬받으려고 시작한 건 아니야. 그래도 박사랑 딴 사람들이 카프카의 노력을 인정해 주니까, 역시 기쁘네!",
                "cn": "无论是园艺还是战斗，这些事最初并不是为了得到夸奖而做的。但是自己的努力能够受到博士和大家的认可，卡夫卡觉得非常高兴。"
            },
            "asset": "char_214_kafka/CN_014"
        },
        {
            "id": "char_214_kafka_CN_017",
            "title": {
                "en": "Added to Squad",
                "jp": "編成",
                "kr": "팀 배치",
                "cn": "编入队伍"
            },
            "text": {
                "en": "Wonder what we can harvest this time?",
                "jp": "今度はどんな収穫があるかなー？",
                "kr": "이번에는 어떤 수확이 있을까~?",
                "cn": "这次又能收获什么好东西呢？"
            },
            "asset": "char_214_kafka/CN_017"
        },
        {
            "id": "char_214_kafka_CN_018",
            "title": {
                "en": "Appointed as Squad Leader",
                "jp": "隊長任命",
                "kr": "팀장 임명",
                "cn": "任命队长"
            },
            "text": {
                "en": "Just leave it to me. I guarantee you're all in for a fun time!",
                "jp": "カフカに任せて、絶対みんなを楽しませてあげるよ。",
                "kr": "카프카에게 맡겨줘, 반드시 모두를 즐겁게 해줄 테니까.",
                "cn": "尽管交给我吧，保证会让大家玩个痛快的。"
            },
            "asset": "char_214_kafka/CN_018"
        },
        {
            "id": "char_214_kafka_CN_019",
            "title": {
                "en": "Depart",
                "jp": "作戦準備",
                "kr": "작전 출발",
                "cn": "行动出发"
            },
            "text": {
                "en": "Ah, thinkin' sucks... I guess I'll be listenin' to you, Doctor.",
                "jp": "頭使うのめんどくさいな……やっぱりドクターの指示に従うよ。",
                "kr": "머리 쓰는 거 귀찮은데에~ 에이 됐다, 그냥 박사가 지시하는 거 따를게.",
                "cn": "动脑子好麻烦啊......所以一切还是听博士的吧。"
            },
            "asset": "char_214_kafka/CN_019"
        },
        {
            "id": "char_214_kafka_CN_020",
            "title": {
                "en": "Begin Operation",
                "jp": "戦闘開始",
                "kr": "작전 개시",
                "cn": "行动开始"
            },
            "text": {
                "en": "Look at all these naughty li'l saplings. Ain'tcha cute... sit tight and Kafka'll trim ya up.",
                "jp": "言うことを聞かない苗木がこんなにたくさん、可愛いね……カフカが剪定してあげるよ～。",
                "kr": "말 안 듣는 묘목이 왜 이렇게 많아~? 귀엽네~ 카프카가 가지치기해 줄게~",
                "cn": "这么多顽劣的树苗吗，真可爱啊......就让卡夫卡来好好修剪你们吧~"
            },
            "asset": "char_214_kafka/CN_020"
        },
        {
            "id": "char_214_kafka_CN_021",
            "title": {
                "en": "Selecting Operator 1",
                "jp": "選択時1",
                "kr": "오퍼레이터 선택 1",
                "cn": "选中干员1"
            },
            "text": {
                "en": "Hmm?",
                "jp": "んん？",
                "kr": "응?",
                "cn": "嗯？"
            },
            "asset": "char_214_kafka/CN_021"
        },
        {
            "id": "char_214_kafka_CN_022",
            "title": {
                "en": "Selecting Operator 2",
                "jp": "選択時2",
                "kr": "오퍼레이터 선택 2",
                "cn": "选中干员2"
            },
            "text": {
                "en": "Kafka, roger!",
                "jp": "カフカ、了解～。",
                "kr": "카프카, 알겠슴다~",
                "cn": "卡夫卡明白~"
            },
            "asset": "char_214_kafka/CN_022"
        },
        {
            "id": "char_214_kafka_CN_023",
            "title": {
                "en": "Deployment 1",
                "jp": "配置1",
                "kr": "배치 1",
                "cn": "部署1"
            },
            "text": {
                "en": "Right here, I guess.",
                "jp": "ここかな。",
                "kr": "여기인가?",
                "cn": "这里吗。"
            },
            "asset": "char_214_kafka/CN_023"
        },
        {
            "id": "char_214_kafka_CN_024",
            "title": {
                "en": "Deployment 2",
                "jp": "配置2",
                "kr": "배치 2",
                "cn": "部署2"
            },
            "text": {
                "en": "Hm-hmmm.",
                "jp": "ふふーん～。",
                "kr": "흐흥~",
                "cn": "哼哼~"
            },
            "asset": "char_214_kafka/CN_024"
        },
        {
            "id": "char_214_kafka_CN_025",
            "title": {
                "en": "In Battle 1",
                "jp": "作戦中1",
                "kr": "작전 중 1",
                "cn": "作战中1"
            },
            "text": {
                "en": "Watch your eyes... I see all your weakpoints in 'em.",
                "jp": "その目……弱点がバレちゃってるよ。",
                "kr": "그 눈…… 약점이 다 보이는걸?",
                "cn": "你的眼神......暴露了你的弱点哦。"
            },
            "asset": "char_214_kafka/CN_025"
        },
        {
            "id": "char_214_kafka_CN_026",
            "title": {
                "en": "In Battle 2",
                "jp": "作戦中2",
                "kr": "작전 중 2",
                "cn": "作战中2"
            },
            "text": {
                "en": "You're all just hedges who know how to walk.",
                "jp": "君たちって、ただの動く生垣じゃん。",
                "kr": "너희는 그냥 움직이는 울타리잖아.",
                "cn": "你们只是会动的树篱嘛~"
            },
            "asset": "char_214_kafka/CN_026"
        },
        {
            "id": "char_214_kafka_CN_027",
            "title": {
                "en": "In Battle 3",
                "jp": "作戦中3",
                "kr": "작전 중 3",
                "cn": "作战中3"
            },
            "text": {
                "en": "Lemme break ya right there.",
                "jp": "折ってあげるよ。",
                "kr": "부러뜨려 줄게.",
                "cn": "让我折断你们。"
            },
            "asset": "char_214_kafka/CN_027"
        },
        {
            "id": "char_214_kafka_CN_028",
            "title": {
                "en": "In Battle 4",
                "jp": "作戦中4",
                "kr": "작전 중 4",
                "cn": "作战中4"
            },
            "text": {
                "en": "Kafka knows you're scared. Tremblin' li'l bare branches.",
                "jp": "カフカには君たちの恐怖がわかるよ、震える枯れ枝たち。",
                "kr": "카프카는 너희의 공포를 느낄 수 있어, 떨고 있는 마른 나뭇가지들.",
                "cn": "卡夫卡知道你在害怕。颤抖的枯枝们。"
            },
            "asset": "char_214_kafka/CN_028"
        },
        {
            "id": "char_214_kafka_CN_029",
            "title": {
                "en": "4-star Result",
                "jp": "高難度作戦クリア",
                "kr": "고난이도 작전 종료",
                "cn": "完成高难行动"
            },
            "text": {
                "en": "Smooth sailin' just like always, Doctor. Alright, makes a Kafka wanna go get 'em!",
                "jp": "ドクターは相変わらず冷静だね。よーし、カフカも頑張るぞー！",
                "kr": "박사는 여전히 냉정하네. 좋았어~ 카프카도 힘내야지~!",
                "cn": "博士还是一如既往地淡定啊。好，我也要加油！"
            },
            "asset": "char_214_kafka/CN_029"
        },
        {
            "id": "char_214_kafka_CN_030",
            "title": {
                "en": "3-star Result",
                "jp": "★3で戦闘終了",
                "kr": "3★ 작전 종료",
                "cn": "3星结束行动"
            },
            "text": {
                "en": "Man, were those enemies pushovers. If I'd known sooner, I coulda saved a Kafka some effort.",
                "jp": "敵ってば弱っちいな。こうなるって知ってたらテキトーに相手してやったのに。",
                "kr": "적이 너무 약한데? 이렇게 될 줄 알았으면 그냥 대충 상대하는 거였는데.",
                "cn": "敌人好弱啊。早知道就随便糊弄一下了。"
            },
            "asset": "char_214_kafka/CN_030"
        },
        {
            "id": "char_214_kafka_CN_031",
            "title": {
                "en": "Sub 3-star Result",
                "jp": "★2以下戦闘終了",
                "kr": "비 3★ 작전 종료",
                "cn": "非3星结束行动"
            },
            "text": {
                "en": "Hmm, guess I gotta be more careful with the pruning next time.",
                "jp": "うーん、今度の剪定はもっと真面目にやらなきゃ。",
                "kr": "음~ 다음 가지치기는 더 열심히 해야겠다.",
                "cn": "唔，下次还要更加认真地修剪才行啊。"
            },
            "asset": "char_214_kafka/CN_031"
        },
        {
            "id": "char_214_kafka_CN_032",
            "title": {
                "en": "Operation Failure",
                "jp": "作戦失敗",
                "kr": "작전 실패",
                "cn": "行动失败"
            },
            "text": {
                "en": "Whaddaya doing, Kafka... you can read their plans, can't you?",
                "jp": "……結局、あいつらの意図を読めなかったってことか。",
                "kr": "……결국, 저 녀석들의 의도를 파악하지 못한 건가.",
                "cn": "......结果，还是没能看穿他们的意图吗。"
            },
            "asset": "char_214_kafka/CN_032"
        },
        {
            "id": "char_214_kafka_CN_033",
            "title": {
                "en": "Assigned to Facility",
                "jp": "基地配属",
                "kr": "시설에 배치",
                "cn": "进驻设施"
            },
            "text": {
                "en": "Where's Silence's lab, again?",
                "jp": "サイレンスの実験室ってどこだっけ？",
                "kr": "사일런스네 실험실이 어디였더라?",
                "cn": "赫默的办公室在哪里来着？"
            },
            "asset": "char_214_kafka/CN_033"
        },
        {
            "id": "char_214_kafka_CN_034",
            "title": {
                "en": "Tap",
                "jp": "タッチ1",
                "kr": "터치",
                "cn": "戳一下"
            },
            "text": {
                "en": "...Whaddaya think you're doin'.",
                "jp": "……何する気なの。",
                "kr": "……뭐 하려고 그러는데?",
                "cn": "......你要干什么啊。"
            },
            "asset": "char_214_kafka/CN_034"
        },
        {
            "id": "char_214_kafka_CN_036",
            "title": {
                "en": "Trust Tap",
                "jp": "信頼タッチ",
                "kr": "신뢰도 터치",
                "cn": "信赖触摸"
            },
            "text": {
                "en": "Doctor, Kafka here wants to deck out your office with some bonsai. Don'tcha worry, I'll make 'em look real good.",
                "jp": "ドクター、執務室にカフカの作った盆栽を飾ろうよ。立派なものを作ってあげるから安心して～！",
                "kr": "박사~ 집무실에 카프카가 만든 분재를 놔두는 건 어때? 멋진 녀석으로 만들어 줄 테니까 안심하라구~!",
                "cn": "博士，卡夫卡想要做盆栽来装点博士的办公室。放心，我会做得很好看的~"
            },
            "asset": "char_214_kafka/CN_036"
        },
        {
            "id": "char_214_kafka_CN_037",
            "title": {
                "en": "Title",
                "jp": "タイトルコール",
                "kr": "타이틀",
                "cn": "标题"
            },
            "text": {
                "en": "Arknights.",
                "jp": "アークナイツ。",
                "kr": "명일방주.",
                "cn": "明日方舟。"
            },
            "asset": "char_214_kafka/CN_037"
        },
        {
            "id": "char_214_kafka_CN_038",
            "title": {
                "en": "New Year's blessing",
                "jp": "新年",
                "kr": "새해",
                "cn": "新年祝福"
            },
            "text": {
                "en": "Doctor, let's build us a snowman! First we roll up two big snowballs. We make the hat kinda round, then we do the clothes reaaal long... Ta-dah, one 'Doctor,' made to order! Oh, I dunno though, feels kinda sad seeing a Doctor all alone on the deck!",
                "jp": "ドクター、カフカと一緒に雪だるまを作ろうよ！そうだね、まずは大きな雪玉を二つ作って……まーるいフードの形を描いて、ながーい裾も足してあげれば……ほら、「ドクター」の出来上がり！あっ、でも、「ドクター」をデッキに独りぼっちにさせたら、ちょっと可哀そうかもね？",
                "kr": "박사, 카프카랑 눈사람 만들자! 우선 큰 눈덩이 두 개를 만들고, 모자는 조금 더 둥그렇게 만든 다음, 긴 옷자락을 늘어뜨리면…… 봐봐, '박사' 완성! 아, 근데 '박사' 혼자 갑판 위에 있으니까 좀 쓸쓸해 보이네.",
                "cn": "博士，我们来一起堆雪人吧！首先搓两个大雪球。帽子要稍微圆一点，然后要修出很长的衣摆......看，一个“博士”就做好啦！啊，不过“博士”一个人被放在甲板上，看上去有点可怜呢！"
            },
            "asset": "char_214_kafka/CN_038"
        },
        {
            "id": "char_214_kafka_CN_042",
            "title": {
                "en": "Greeting",
                "jp": "挨拶",
                "kr": "인사",
                "cn": "问候"
            },
            "text": {
                "en": "What work you got for me today, Doctor?",
                "jp": "今日はどんな仕事やらせてくれるの、ドクター？",
                "kr": "오늘은 어떤 일을 시킬 거야, 박사?",
                "cn": "今天安排了什么工作给我吗，博士？"
            },
            "asset": "char_214_kafka/CN_042"
        },
        {
            "id": "char_214_kafka_CN_044",
            "title": {
                "en": "Anniversary Celebration",
                "jp": "周年",
                "kr": "애니버서리",
                "cn": "周年庆典"
            },
            "text": {
                "en": "Yannow, I've been here long enough to see all you Rhodes Islanders are real good people. And nothing gets me more heated than good people getting bullied. So if there's ever any bad guys you just can't handle, you drop me a line. A Kafka's always saving some secret sauce—what, no need? Fine. You're the boss, boss.",
                "jp": "ここに来てからだいぶ経つけど、ロドスは本当にいい人ばかりだよ。カフカが一番許せないのは、そういういい人がいじめられることなんだ。だからドクター、手に負えないような悪いやつに出くわしたら頼ってね。カフカにはとっておきの手が――そんなことしなくてもいいって？んー、わかったよ。",
                "kr": "카프카가 여기 온 지 꽤 됐는데, 로도스 아일랜드에는 좋은 사람이 참 많은 것 같아. 좋은 사람이 괴롭힘을 당하는 건 카프카가 가장 용납할 수 없는 일이야. 박사, 혹시 상대하기 어려운 나쁜 사람이 있으면 카프카한테 말해. 카프카가 특별한 방법으로…… 그러지 말라고? 알겠어, 박사 말 들을게.",
                "cn": "来到这里有一段时间了，发现罗德岛各位都是很好的人呢。好人受到欺负，是我最不能容忍的事。博士，如果有什么无法解决的坏人，就来找我吧。我有一些特殊的手段——不用这样？好吧，听你的。"
            },
            "asset": "char_214_kafka/CN_044"
        }
    ],
    "actors": {
        "en": {
            "native": "Abby Trott",
            "global": "Abby Trott"
        },
        "cn": {
            "native": "皛四白",
            "global": "Shi Haku"
        },
        "jp": {
            "native": "富田美憂",
            "global": "Miyu Tomita"
        },
        "kr": {
            "native": "우정신",
            "global": "Woo Jeong-sin"
        }
    },
    "availability": [
        "en",
        "cn",
        "jp",
        "kr"
    ]
}