{
    "charid": "char_109_fmout",
    "nameid": "fmout",
    "names": {
        "en": "Gitano",
        "jp": "ギターノ",
        "kr": "기타노",
        "cn": "远山"
    },
    "voices": [
        {
            "id": "char_109_fmout_CN_001",
            "title": {
                "en": "Appointed as Assistant",
                "jp": "秘書任命",
                "kr": "어시스턴트 임명",
                "cn": "任命助理"
            },
            "text": {
                "en": "Alright, Doctor, your tarot card for today is...",
                "jp": "さて、ドクター、おぬしの今日の運勢は……。",
                "kr": "자아, 박사. 그대의 오늘 운세는…",
                "cn": "嗯，博士。您今天的运势是......"
            },
            "asset": "char_109_fmout/CN_001"
        },
        {
            "id": "char_109_fmout_CN_002",
            "title": {
                "en": "Talk 1",
                "jp": "会話1",
                "kr": "대화 1",
                "cn": "交谈1"
            },
            "text": {
                "en": "Would you like to learn more about your future?",
                "jp": "おぬしも未来の運命を知りたいのか……。",
                "kr": "그대도 미래의 운명을 알고 싶은 것인가…",
                "cn": "您也想知道，自己未来的命运吗......"
            },
            "asset": "char_109_fmout/CN_002"
        },
        {
            "id": "char_109_fmout_CN_003",
            "title": {
                "en": "Talk 2",
                "jp": "会話2",
                "kr": "대화 2",
                "cn": "交谈2"
            },
            "text": {
                "en": "Bear it in mind that excessive reliance on unfathomed power will eventually backfire on us.",
                "jp": "ゆめゆめ忘れぬことじゃ。未知なる力による反作用は、おぬしたちに牙を剥くこともあると。",
                "kr": "반드시 기억해 두게나. 미지의 힘에 의한 반작용은 도리어 그대들에게 해가 되는 경우도 있다는 것을.",
                "cn": "随时都别忘记......未知的力量引起的反作用，很可能反噬我们自身。"
            },
            "asset": "char_109_fmout/CN_003"
        },
        {
            "id": "char_109_fmout_CN_004",
            "title": {
                "en": "Talk 3",
                "jp": "会話3",
                "kr": "대화 3",
                "cn": "交谈3"
            },
            "text": {
                "en": "Tarot cards aren't divine, all-seeing tools. Instead, we use them for guidance when we feel lost.",
                "jp": "タロットは、あくまで心に立ち込める霧を晴らしてくれるだけ。万能の神にはなり得ぬ。",
                "kr": "타로는 어디까지나 마음속 뿌연 안개를 걷어줄 뿐. 전지전능한 신이 아닐세.",
                "cn": "塔罗只能祛除内心的雾霭，却从来不曾拥有万事皆能的神性。"
            },
            "asset": "char_109_fmout/CN_004"
        },
        {
            "id": "char_109_fmout_CN_005",
            "title": {
                "en": "Talk after Promotion 1",
                "jp": "昇進後会話1",
                "kr": "1차 정예화 후 대화",
                "cn": "晋升后交谈1"
            },
            "text": {
                "en": "Destiny is like the world we walk upon—no one can escape it.",
                "jp": "運命とは大地のようなものじゃ。そのくびきから逃れられるものは、誰一人としておらぬ。",
                "kr": "운명이란 대지와도 같은 것이네. 그 속박에서 벗어날 수 있는 건 아무도 없지.",
                "cn": "命运就像大地，谁也不能挣脱它的枷锁。"
            },
            "asset": "char_109_fmout/CN_005"
        },
        {
            "id": "char_109_fmout_CN_006",
            "title": {
                "en": "Talk after Promotion 2",
                "jp": "昇進後会話2",
                "kr": "2차 정예화 후 대화",
                "cn": "晋升后交谈2"
            },
            "text": {
                "en": "Humans might never be able to escape this world... but we can change it. Our actions belie endless possibilities.",
                "jp": "人は、大地のくびきからは逃れられぬ。じゃが、大地そのものを変えてしまうことはできる。それに秘められたるは、無数の可能性じゃ。",
                "kr": "인간은 대지의 속박에서 벗어날 수 없는 법. 허나, 대지 그 자체를 바꿔버릴 순 있지. 그 안에 감춰진 건, 바로 무한한 가능성이네.",
                "cn": "人无法挣脱大地的桎梏，却能改变大地的样貌。人类的行为中潜藏着无数的可能性。"
            },
            "asset": "char_109_fmout/CN_006"
        },
        {
            "id": "char_109_fmout_CN_007",
            "title": {
                "en": "Talk after Trust Increase 1",
                "jp": "信頼上昇後会話1",
                "kr": "신뢰도 상승 후 대화 1",
                "cn": "信赖提升后交谈1"
            },
            "text": {
                "en": "There are countless topics for which you can consult the tarot, the most common one being your luck in card games. To change it, however, you must be brave enough to change your fate first.",
                "jp": "占いには、様々な手法がある……手立てとしてはタロットが一番多いのう。もしタロットの結果を変えたいというのなら、運命そのものを変えようとする勇気が必要じゃ。",
                "kr": "점을 보는 방법엔 여러 가지가 있다네…… 그중엔 타로가 가장 대표적이지. 만일 타로의 결과를 바꾸고 싶다면, 운명 그 자체를 바꾸고자 하는 용기가 필요할 걸세.",
                "cn": "运势中，存有无数主题，而最常见的就是......牌运。若要改变牌运，就要勇于改变命运。"
            },
            "asset": "char_109_fmout/CN_007"
        },
        {
            "id": "char_109_fmout_CN_008",
            "title": {
                "en": "Talk after Trust Increase 2",
                "jp": "信頼上昇後会話2",
                "kr": "신뢰도 상승 후 대화 2",
                "cn": "信赖提升后交谈2"
            },
            "text": {
                "en": "We have a ritual among diviners that's all the rage these days. We call it the 'Hand of Fate.' Would you like to try it?",
                "jp": "最近占い師の間で流行りの儀式、わらわたちは「運命の手」と呼んでおる。試してみるか？",
                "kr": "요즘 점술가들 사이에서 유행하는 의식이 있는데, 우리는 그걸 '운명의 손'이라 부르고 있지. 한번 해 보겠나?",
                "cn": "最近在占卜师之间有一个流行的仪式，我们称之为“命运之手”，您想试试看吗？"
            },
            "asset": "char_109_fmout/CN_008"
        },
        {
            "id": "char_109_fmout_CN_009",
            "title": {
                "en": "Talk after Trust Increase 3",
                "jp": "信頼上昇後会話3",
                "kr": "신뢰도 상승 후 대화 3",
                "cn": "信赖提升后交谈3"
            },
            "text": {
                "en": "It's a divination taboo to do readings concerning death. But I don't believe death is the end—it's the beginning of something new.",
                "jp": "「死」を占うことは、占い師の間ではタブーとされておる。じゃがわらわは、「死」は終わりではなく、新たな始まりと考えておる……。",
                "kr": "…'죽음'을 점치는 건 점술가들 사이에선 금기시되어 있지. 다만, 우린 ‘죽음’을 끝이 아닌 새로운 시작으로 여긴다네…",
                "cn": "对“死亡”的占卜，在我们业内也算是种禁忌。但我认为，“死亡”并非终点，而是一个新的开始。"
            },
            "asset": "char_109_fmout/CN_009"
        },
        {
            "id": "char_109_fmout_CN_010",
            "title": {
                "en": "Idle",
                "jp": "放置",
                "kr": "방치",
                "cn": "闲置"
            },
            "text": {
                "en": "Dreams can often enlighten you in strange ways. If you have an enlightening dream like that, you'd best remember every detail, Doctor.",
                "jp": "夢からは、稀に面白い啓示が得られることもある。見た夢はしっかりと記憶に留めておくのじゃ、ドクター。",
                "kr": "꿈에선 아주 가끔 흥미로운 계시를 얻을 수 있지. 꾼 꿈은 잘 기억해두는 게 좋을 걸세, 박사…",
                "cn": "偶尔，梦境会为你展示有趣的启示，如果体验了这样的梦，要好好保存在记忆中哦，博士。"
            },
            "asset": "char_109_fmout/CN_010"
        },
        {
            "id": "char_109_fmout_CN_011",
            "title": {
                "en": "Onboard",
                "jp": "入職会話",
                "kr": "오퍼레이터 입사",
                "cn": "干员报到"
            },
            "text": {
                "en": "Following the guidance of the arcana, our paths have finally converged. Nice to meet you, Doctor.",
                "jp": "アルカナの導きにより、ようやくおぬしとわらわの運命が交わるのじゃな、ドクター。",
                "kr": "아르카나의 인도 아래 드디어 그대와 내 운명이 엇갈리게 되었군, 박사.",
                "cn": "遵从阿尔克纳的指引，我的命运终于与您交汇了，博士。"
            },
            "asset": "char_109_fmout/CN_011"
        },
        {
            "id": "char_109_fmout_CN_012",
            "title": {
                "en": "Watching Battle Record",
                "jp": "経験値上昇",
                "kr": "작전기록 학습",
                "cn": "观看作战记录"
            },
            "text": {
                "en": "I feel inspired now.",
                "jp": "霊感の高まりを感じるぞ。",
                "kr": "영감이 강해진 게 느껴지는군.",
                "cn": "有灵感了呢。"
            },
            "asset": "char_109_fmout/CN_012"
        },
        {
            "id": "char_109_fmout_CN_013",
            "title": {
                "en": "Promotion 1",
                "jp": "昇進Ⅰ",
                "kr": "1차 정예화 (승진)",
                "cn": "精英化晋升1"
            },
            "text": {
                "en": "I'd already foreseen this promotion in my crystal ball. Heheh, just kidding.",
                "jp": "わらわの水晶が、この昇進の光景を映しておったぞ……。ふふ、ただの冗談じゃ。",
                "kr": "내 수정구슬이 이미 승진하는 모습을 비춰주고 있었다네…… 후후, 농담 한 번 해본 걸세.",
                "cn": "我已经在水晶里预见了这次晋升哦？呵呵，只是个玩笑而已。"
            },
            "asset": "char_109_fmout/CN_013"
        },
        {
            "id": "char_109_fmout_CN_014",
            "title": {
                "en": "Promotion 2",
                "jp": "昇進Ⅱ",
                "kr": "2차 정예화 (승진)",
                "cn": "精英化晋升2"
            },
            "text": {
                "en": "You want to know your destiny, Doctor? Too bad, I can't help you. I'm not the one to share it with you, for the fate forbids me to do so.",
                "jp": "ドクター、自らの運命の往く先を見たいと言うのか？残念じゃが、わらわは力になれん。その秘密を明かすのは、わらわの役目ではないのでな。",
                "kr": "박사, 운명이 어디로 흘러가는지 보고 싶은가? 아쉽지만 그건 어렵다네. 그대의 운명에 얽힌 비밀을 밝혀내는 건 내 역할이 아니니 말일세.",
                "cn": "博士，你想知晓......自己的命运终将去往何方？很遗憾，我帮不了你。为你揭示那些秘密，并不是我的使命。"
            },
            "asset": "char_109_fmout/CN_014"
        },
        {
            "id": "char_109_fmout_CN_017",
            "title": {
                "en": "Added to Squad",
                "jp": "編成",
                "kr": "팀 배치",
                "cn": "编入队伍"
            },
            "text": {
                "en": "Wait a minute, let me predict the results of this battle.",
                "jp": "しばし待たれい、この作戦の行く末を占おう。",
                "kr": "잠시 기다려 주게, 이 작전의 결말을 점쳐 볼 테니.",
                "cn": "请稍候，先来占卜一下这次战斗的结果吧。"
            },
            "asset": "char_109_fmout/CN_017"
        },
        {
            "id": "char_109_fmout_CN_018",
            "title": {
                "en": "Appointed as Squad Leader",
                "jp": "隊長任命",
                "kr": "팀장 임명",
                "cn": "任命队长"
            },
            "text": {
                "en": "Well then, let me pray for everyone.",
                "jp": "さて、皆の為に祈祷でもしようかのう。",
                "kr": "자 그럼, 모두를 위해 기도라도 올려보도록 할까.",
                "cn": "那么，就让我来为大家祈祷吧。"
            },
            "asset": "char_109_fmout/CN_018"
        },
        {
            "id": "char_109_fmout_CN_019",
            "title": {
                "en": "Depart",
                "jp": "作戦準備",
                "kr": "작전 출발",
                "cn": "行动出发"
            },
            "text": {
                "en": "Fate is a fickle thing... only the victorious will be forever revered.",
                "jp": "運命とは、有為転変のもの。世に残るのは勝者だけじゃ。",
                "kr": "운명이란 항상 변하기 마련이네. 세상에 끝까지 남는 건 승자뿐이지.",
                "cn": "命运变幻无常，唯有胜者永存于世。"
            },
            "asset": "char_109_fmout/CN_019"
        },
        {
            "id": "char_109_fmout_CN_020",
            "title": {
                "en": "Begin Operation",
                "jp": "戦闘開始",
                "kr": "작전 개시",
                "cn": "行动开始"
            },
            "text": {
                "en": "I can see the outcome. Victory belongs to Rhodes Island.",
                "jp": "わらわには、ロドスの勝利がみえるぞ。",
                "kr": "내겐 로도스 아일랜드의 승리가 보이네.",
                "cn": "我看到了结果。胜利属于罗德岛。"
            },
            "asset": "char_109_fmout/CN_020"
        },
        {
            "id": "char_109_fmout_CN_021",
            "title": {
                "en": "Selecting Operator 1",
                "jp": "選択時1",
                "kr": "오퍼레이터 선택 1",
                "cn": "选中干员1"
            },
            "text": {
                "en": "A very wise choice.",
                "jp": "賢明な判断じゃ。",
                "kr": "현명한 판단일세.",
                "cn": "明智的选择。"
            },
            "asset": "char_109_fmout/CN_021"
        },
        {
            "id": "char_109_fmout_CN_022",
            "title": {
                "en": "Selecting Operator 2",
                "jp": "選択時2",
                "kr": "오퍼레이터 선택 2",
                "cn": "选中干员2"
            },
            "text": {
                "en": "My turn.",
                "jp": "わらわの出番じゃ。",
                "kr": "내 차례가 왔군.",
                "cn": "我的回合。"
            },
            "asset": "char_109_fmout/CN_022"
        },
        {
            "id": "char_109_fmout_CN_023",
            "title": {
                "en": "Deployment 1",
                "jp": "配置1",
                "kr": "배치 1",
                "cn": "部署1"
            },
            "text": {
                "en": "Draw a card.",
                "jp": "カードを引くがよい。",
                "kr": "카드를 뽑게나.",
                "cn": "抽一张卡片。"
            },
            "asset": "char_109_fmout/CN_023"
        },
        {
            "id": "char_109_fmout_CN_024",
            "title": {
                "en": "Deployment 2",
                "jp": "配置2",
                "kr": "배치 2",
                "cn": "部署2"
            },
            "text": {
                "en": "Do not resist your fate.",
                "jp": "運命に抗うなかれ。",
                "kr": "운명을 거스르지 말지어다.",
                "cn": "不要违抗你的命运。"
            },
            "asset": "char_109_fmout/CN_024"
        },
        {
            "id": "char_109_fmout_CN_025",
            "title": {
                "en": "In Battle 1",
                "jp": "作戦中1",
                "kr": "작전 중 1",
                "cn": "作战中1"
            },
            "text": {
                "en": "The tower of void.",
                "jp": "虚空の「塔」よ。",
                "kr": "허공의 '탑'이여.",
                "cn": "虚空之塔。"
            },
            "asset": "char_109_fmout/CN_025"
        },
        {
            "id": "char_109_fmout_CN_026",
            "title": {
                "en": "In Battle 2",
                "jp": "作戦中2",
                "kr": "작전 중 2",
                "cn": "作战中2"
            },
            "text": {
                "en": "The flying chariot.",
                "jp": "「戦車」よ、空を駆けよ。",
                "kr": "'전차'여, 하늘을 달려라.",
                "cn": "行空之战车。"
            },
            "asset": "char_109_fmout/CN_026"
        },
        {
            "id": "char_109_fmout_CN_027",
            "title": {
                "en": "In Battle 3",
                "jp": "作戦中3",
                "kr": "작전 중 3",
                "cn": "作战中3"
            },
            "text": {
                "en": "The Emperor's scepter shall break.",
                "jp": "「皇帝」の王笏をへし折れ。",
                "kr": "'황제'의 왕홀을 꺾어 버려라.",
                "cn": "折断帝王的权杖。"
            },
            "asset": "char_109_fmout/CN_027"
        },
        {
            "id": "char_109_fmout_CN_028",
            "title": {
                "en": "In Battle 4",
                "jp": "作戦中4",
                "kr": "작전 중 4",
                "cn": "作战中4"
            },
            "text": {
                "en": "All will fall before the Priestess's might.",
                "jp": "万物を滅ぼせ、「女教皇」よ。",
                "kr": "만물을 멸하라, '여사제'여.",
                "cn": "女祭司毁灭一切。"
            },
            "asset": "char_109_fmout/CN_028"
        },
        {
            "id": "char_109_fmout_CN_029",
            "title": {
                "en": "4-star Result",
                "jp": "高難度作戦クリア",
                "kr": "고난이도 작전 종료",
                "cn": "完成高难行动"
            },
            "text": {
                "en": "Will fate have us in a chokehold… or will we turn the table?",
                "jp": "運命にねじ伏せられるのか、それとも絶望の地より迎え撃つのか？",
                "kr": "운명에 굴복하겠는가, 아니면 절망의 땅으로부터 맞서 싸우겠는가?",
                "cn": "是命运扼住我们的咽喉，亦或是，我们将要对命运作绝地反击？"
            },
            "asset": "char_109_fmout/CN_029"
        },
        {
            "id": "char_109_fmout_CN_030",
            "title": {
                "en": "3-star Result",
                "jp": "★3で戦闘終了",
                "kr": "3★ 작전 종료",
                "cn": "3星结束行动"
            },
            "text": {
                "en": "I have moved all of them to the graveyard.",
                "jp": "あの手合らは、すでに墓標の下へ送ったぞ。",
                "kr": "하찮은 것들은 이미 묘비 아래로 보내버렸다네.",
                "cn": "我已经将他们全部移动到墓地之中了。"
            },
            "asset": "char_109_fmout/CN_030"
        },
        {
            "id": "char_109_fmout_CN_031",
            "title": {
                "en": "Sub 3-star Result",
                "jp": "★2以下戦闘終了",
                "kr": "비 3★ 작전 종료",
                "cn": "非3星结束行动"
            },
            "text": {
                "en": "Time to reshuffle the deck.",
                "jp": "さて、シャッフルのときじゃ。",
                "kr": "자, 카드를 섞을 시간일세.",
                "cn": "该重新洗牌了。"
            },
            "asset": "char_109_fmout/CN_031"
        },
        {
            "id": "char_109_fmout_CN_032",
            "title": {
                "en": "Operation Failure",
                "jp": "作戦失敗",
                "kr": "작전 실패",
                "cn": "行动失败"
            },
            "text": {
                "en": "Impossible... this isn't what I saw in the cards...",
                "jp": "わらわたちの運命は、こんなものでは……。",
                "kr": "우리의 운명은, 이럴 리가 없을 터인데……",
                "cn": "不，这不该是我们应有的命运......"
            },
            "asset": "char_109_fmout/CN_032"
        },
        {
            "id": "char_109_fmout_CN_033",
            "title": {
                "en": "Assigned to Facility",
                "jp": "基地配属",
                "kr": "시설에 배치",
                "cn": "进驻设施"
            },
            "text": {
                "en": "Bad omens seem to lurk inside this room. May I use my powers to help you manage them?",
                "jp": "この部屋には、おぬしに降りかかる災厄が潜んでおるように見える。わらわが力になってやってもよいぞ？",
                "kr": "이 방엔 그대에게 미칠 불운이 숨어 있는 모양일세. 내가 좀 도와줘도 괜찮네만?",
                "cn": "这个房间里面似乎潜藏着厄运，需要我用我的力量帮你做点什么吗？"
            },
            "asset": "char_109_fmout/CN_033"
        },
        {
            "id": "char_109_fmout_CN_034",
            "title": {
                "en": "Tap",
                "jp": "タッチ1",
                "kr": "터치",
                "cn": "戳一下"
            },
            "text": {
                "en": "Hm? What can I do for you?",
                "jp": "ふむ、どうかしたか？",
                "kr": "흐음, 무슨 일이라도 있는 겐가?",
                "cn": "嗯？怎么了？"
            },
            "asset": "char_109_fmout/CN_034"
        },
        {
            "id": "char_109_fmout_CN_036",
            "title": {
                "en": "Trust Tap",
                "jp": "信頼タッチ",
                "kr": "신뢰도 터치",
                "cn": "信赖触摸"
            },
            "text": {
                "en": "Want me to do a reading on your future? All right, please give me a minute.",
                "jp": "今後の運勢を占ってほしいじゃと？そうか、しばし待っておれ。",
                "kr": "앞으로의 운세를 점쳐달라는 말인가? 알겠네, 잠시 기다려 보게.",
                "cn": "想让我为您占卜下今后的运气？是嘛~请稍等一下。"
            },
            "asset": "char_109_fmout/CN_036"
        },
        {
            "id": "char_109_fmout_CN_037",
            "title": {
                "en": "Title",
                "jp": "タイトルコール",
                "kr": "타이틀",
                "cn": "标题"
            },
            "text": {
                "en": "Arknights.",
                "jp": "アークナイツ。",
                "kr": "명일방주.",
                "cn": "明日方舟。"
            },
            "asset": "char_109_fmout/CN_037"
        },
        {
            "id": "char_109_fmout_CN_042",
            "title": {
                "en": "Greeting",
                "jp": "挨拶",
                "kr": "인사",
                "cn": "问候"
            },
            "text": {
                "en": "Doctor, you're blessed by the winds of luck.",
                "jp": "幸運の風が吹いておるぞ、ドクター。",
                "kr": "행운의 바람이 불고 있네, 박사.",
                "cn": "幸运之风吹拂着你，博士。"
            },
            "asset": "char_109_fmout/CN_042"
        }
    ],
    "actors": {
        "en": {
            "native": "Sarah Ovens",
            "global": "Sarah Ovens"
        },
        "cn": {
            "native": "徐慧",
            "global": "Chris Xu"
        },
        "jp": {
            "native": "優木かな",
            "global": "Kana Yuuki"
        },
        "kr": {
            "native": "김보나",
            "global": "Kim Bo-na"
        }
    },
    "availability": [
        "en",
        "cn",
        "jp",
        "kr"
    ]
}