{
    "charid": "char_4063_quartz",
    "nameid": "quartz",
    "names": {
        "en": "Quartz",
        "jp": "クォーツ",
        "kr": "쿼츠",
        "cn": "石英"
    },
    "voices": [
        {
            "id": "char_4063_quartz_CN_001",
            "title": {
                "en": "Appointed as Assistant",
                "jp": "秘書任命",
                "kr": "어시스턴트 임명",
                "cn": "任命助理"
            },
            "text": {
                "en": "I'm not the greatest at desk work, but if all you need is someone to stay by your side and help you put your tasks and schedule in order, I can give it a shot.",
                "jp": "机仕事はあまり得意じゃない。が、あなたに付き添って、業務スケジュールの作成や管理を手伝うだけなら、やれなくもないと思う。",
                "kr": "서류 업무는 그다지 잘하는 편이 아니지만, 당신 옆에서 스케줄 배정이나 관리를 돕는 정도라면, 해 볼 수 있을 것 같아.",
                "cn": "文书工作我不太在行，但如果只是陪在您身边，帮着安排和把控处理各项事务的时间，我想我可以试试看。"
            },
            "asset": "char_4063_quartz/CN_001"
        },
        {
            "id": "char_4063_quartz_CN_002",
            "title": {
                "en": "Talk 1",
                "jp": "会話1",
                "kr": "대화 1",
                "cn": "交谈1"
            },
            "text": {
                "en": "This pocket watch? My old man gave it to me before he left home. It's nothing fancy, but it keeps time. It does need to be maintained and have its face cleaned every now and then... Doctor, is there anyone at Rhodes Island who can fix watches?",
                "jp": "この懐中時計が気になるのか？これは父が家を出る前に私にくれた物だ。大した値打ちはないが、時間は正確なんだ。ただ、やはり定期的なオーバーホールは必要だし、ケースのクリーニングも……というわけでドクター、ロドスに時計の修理が得意な者はいるか？",
                "kr": "이 회중시계……? 이건 아버지가 집을 떠나기 전에 주신 거야. 돈이 되는 물건은 아니지만, 시간은 정확하지. 다만 정기적으로 점검이 필요하고, 케이스 청소도 해야 돼…… 그래서 말인데 박사, 로도스 아일랜드에 혹시 시계 수리에 대해 잘 아는 사람 있어?",
                "cn": "这块怀表吗？是爸爸离开家之前留给我的，不是什么值钱玩意，但走时很准，只是需要定期保养机芯、清洁表盘......博士，罗德岛上有精通钟表修理的人吗？"
            },
            "asset": "char_4063_quartz/CN_002"
        },
        {
            "id": "char_4063_quartz_CN_003",
            "title": {
                "en": "Talk 2",
                "jp": "会話2",
                "kr": "대화 2",
                "cn": "交谈2"
            },
            "text": {
                "en": "You can leave the cooking to me, when we're out on field missions. Back when I was in the Columbian barrenlands, I was always in charge of catering. I can't make any guarantees when it comes to taste, but it won't leave you with a stomachache, at least.",
                "jp": "野外任務なら、賄いは私に任せてもいいぞ。クルビアの荒野にいた頃は、チームの炊事を担っていたからな。味はそこまで保証できないが、腹を壊すようなことは決してない。",
                "kr": "야외 임무라면, 취사는 나한테 맡겨. 컬럼비아의 황야에 있을 땐 내가 취사 담당이었으니까. 맛은 보장 못 해도, 배탈이 나는 일은 절대 없을 거야.",
                "cn": "在野外执行任务的话，做饭的事情可以交给我，以前在哥伦比亚荒野的时候，一直是我在负责这个。不保证有多美味，但绝不会拉肚子。"
            },
            "asset": "char_4063_quartz/CN_003"
        },
        {
            "id": "char_4063_quartz_CN_004",
            "title": {
                "en": "Talk 3",
                "jp": "会話3",
                "kr": "대화 3",
                "cn": "交谈3"
            },
            "text": {
                "en": "Back when I was with the Pioneer Team, we got into it with the company over how they supplied us. We ended up escaping into the barrenlands. That's when I lost my eye. It's not a disgrace, but it's not an honor, either. It's just the kind of misfortune that us regular Columbian folks often have to suffer, only a bit more conspicuous than usual.",
                "jp": "開拓隊にいた頃、補給物資が不当な中抜きをされていて揉め事になり、荒野へ逃げ延びた。この目の傷はその時に残したものだ。恥の象徴というほどではないが、誇るべきものでもない。クルビアの一般市民にとってはありふれた、「良くない」巡り合わせの証さ……たまたま目立つ場所にあるだけのな。",
                "kr": "개척팀에 있었을 때 회사가 보급 물자를 떼먹어서 트러블이 생겼었어. 그래서 황야로 도망치게 됐던 거고, 이 상처는 그때 생긴 거야. 이런 건 컬럼비아인들이 흔히 겪는 '나쁜'일에 불과하니까 딱히 수치스럽지도, 자랑스럽지도 않아. 그냥 어쩌다 보니 상처가 눈에 띄는 곳에 생겼을 뿐이야.",
                "cn": "拓荒队的补给被克扣，我们和公司起了冲突，逃进了荒野，这道伤便是当时留下的。它并非耻辱，也不算什么荣耀，它只是哥伦比亚普通人常有的“不好的”遭遇，不过在显眼的位置罢了。"
            },
            "asset": "char_4063_quartz/CN_004"
        },
        {
            "id": "char_4063_quartz_CN_005",
            "title": {
                "en": "Talk after Promotion 1",
                "jp": "昇進後会話1",
                "kr": "1차 정예화 후 대화",
                "cn": "晋升后交谈1"
            },
            "text": {
                "en": "Planning your time and planning your life couldn't be more different. When you're eking out a living, you've got no choice but to use every last second. All your free time is spent watching the clock. On the other hand, to plan out your life, you need enough time to think and feel. Those aren't contradictory. It's just the second one's more of a luxury to most people.",
                "jp": "時間管理と人生設計は、全くの別物だ。今日を生きるのに精いっぱいな者は一秒たりとも無駄にできない。手を止めてぼうっとする時も、じっと時計を見ながらだ。しかし一方、人生の方向性を定めるに必要なのは、じっくり考え、多く経験するための時間なんだ。両者は矛盾こそしないが、ただ後者は多くの人にとっては贅沢に思えるだろう。",
                "kr": "시간을 관리하는 거랑 인생을 계획하는 건 별개의 문제야. 오늘을 살기 위해 1초도 허투루 쓸 수 없는 사람은 멍때릴 시간조차 없겠지만, 인생을 계획하려면 오랜 시간을 들여 생각과 경험을 쌓아야 하지. 이 두 가지가 서로 모순되진 않지만, 후자는 아마 많은 사람들에겐 사치일 거야.",
                "cn": "规划时间和规划人生是两码事。讨生活的人不得不把每一秒钟都利用起来，连发个呆都要掐着表，而规划人生，恰恰需要足够多的时间去思考和感受。两者并不矛盾，只是后者对于多数人来说更奢侈。"
            },
            "asset": "char_4063_quartz/CN_005"
        },
        {
            "id": "char_4063_quartz_CN_006",
            "title": {
                "en": "Talk after Promotion 2",
                "jp": "昇進後会話2",
                "kr": "2차 정예화 후 대화",
                "cn": "晋升后交谈2"
            },
            "text": {
                "en": "Is my sword heavy? 'course it is. But I need a heavy one to protect my friends and defend our overdue freedom. The truer the weight I carry is, the mightier I can wield it... Of course, when I'm hurt, it also comes in handy as a walking stick.",
                "jp": "この剣が重くないかって？重いに決まってるさ。だが私には必要な重さだ。仲間を守るためにも、やっと得られたこの自由を守り抜くためにもな。それらの重みを背に感じることで、より力強く剣を振り下ろせる……もちろん、ケガした時は杖にも使えるよ。",
                "kr": "이 검이 무겁지 않냐고? 당연히 무거워. 하지만 내 동료들, 그리고 뒤늦게 얻은 자유를 지키기 위해서라도, 이 검은 꼭 필요한 존재야. 짊어진 것들의 무게를 느끼는 것만으로도, 더 강하게 검을 휘두를 수 있어…… 물론, 다쳤을 땐 지팡이로도 사용할 수 있고.",
                "cn": "您问这柄剑重不重？当然重了。但我需要这么一柄剑，去保护我的同伴，捍卫迟来的自由。背负的重量越真实，挥动它的时候也就越有力......当然受伤的时候，也更方便当作拐杖。"
            },
            "asset": "char_4063_quartz/CN_006"
        },
        {
            "id": "char_4063_quartz_CN_007",
            "title": {
                "en": "Talk after Trust Increase 1",
                "jp": "信頼上昇後会話1",
                "kr": "신뢰도 상승 후 대화 1",
                "cn": "信赖提升后交谈1"
            },
            "text": {
                "en": "When my mother died, I didn't even get to mourn her. I had a huge pile of medical debt waiting for me to pay off. Why did I join the Pioneer Team, and why did I become a merc? Because I had no other choice. Of course, I came to Rhodes Island after giving it serious thought.",
                "jp": "母が亡くなった時は、悲しむ余裕すらなかった。巨額の医療費の支払いが迫っていたからな。なぜ開拓隊に入ったのか、そしてフリーの傭兵になったのか。それは、ほかに選択肢がなかったからだ。でも、ロドスに来たのは、ちゃんと慎重に考えた末に出した結論だよ。",
                "kr": "어머니가 돌아가셨을 때, 난 슬퍼할 겨를조차 없었어. 거액의 의료비를 지불해야 했었거든. 왜 개척대에 들어가고, 자유 용병이 됐었냐고? 그야 다른 선택지가 없었거든. 그래도 로도스 아일랜드에 오기로 한 건, 신중하게 고민하고 내린 결정이었어.",
                "cn": "妈妈去世时，我甚至顾不上难过，毕竟还有巨额的医疗费用等着我去结清。为什么加入拓荒队，为什么成为自由佣兵？因为没有别的选择。当然，来罗德岛，是我自己慎重考虑后的决定。"
            },
            "asset": "char_4063_quartz/CN_007"
        },
        {
            "id": "char_4063_quartz_CN_008",
            "title": {
                "en": "Talk after Trust Increase 2",
                "jp": "信頼上昇後会話2",
                "kr": "신뢰도 상승 후 대화 2",
                "cn": "信赖提升后交谈2"
            },
            "text": {
                "en": "A free mercenary only takes a mission she thinks is worth it. There was this one night when I was affixing some beast teeth to my sword by the fire while my friends slept, my watch ticking away. Time is always on my mind, but that was the first time I really felt its passing.",
                "jp": "フリーの傭兵は、やる価値があると認識した任務しか引き受けない。ある晩、私は篝火の傍に座って、集めた獣の牙を剣に取り付けていた。仲間は皆眠りについて、この時計だけがチクタクと時を刻んでいた……私は昔から時間を気にするタチではあったが、流れゆく時を明確に感じたのは、その時が初めてだったよ。",
                "kr": "자유 용병은 수행할 가치가 있다고 여기는 임무만 받아. 횃불 옆에 앉아 모아온 짐승의 이빨을 검에 달고 있었던 어느 날 밤, 동료들은 전부 잠들었고, 오직 이 시계만이 째깍째깍 움직이고 있었지. 예전부터 난 시간을 신경 쓰는 편이긴 했지만, 시간의 흐름을 명확하게 느꼈던 건 그때가 처음이었어.",
                "cn": "自由佣兵只接自己认为有价值的任务。晚上，我在火堆边将收集来的兽牙装在剑上，同伴们都睡着了，只有这块表在嘀嗒嘀嗒地走着。我以前就很在意时间，但那是我第一次真切感受到它的流逝。"
            },
            "asset": "char_4063_quartz/CN_008"
        },
        {
            "id": "char_4063_quartz_CN_009",
            "title": {
                "en": "Talk after Trust Increase 3",
                "jp": "信頼上昇後会話3",
                "kr": "신뢰도 상승 후 대화 3",
                "cn": "信赖提升后交谈3"
            },
            "text": {
                "en": "Disbandment is inevitable. Without a clear goal and strict discipline, a mercenary can't survive the wilderness... Maybe only an organization like Rhodes Island can really protect what's beautiful out there. I'm thankful that I could come here.",
                "jp": "解散は必然だった。明確な目標もなければ、厳格な規律もなかった。そんな傭兵の集まりが荒野を生き抜くのは所詮無理な話だ……きっと、ロドスみたいな組織でもない限り、真に美しいものは守り抜けないだろう。ここに来れて、つくづく幸運に感じているんだ。",
                "kr": "해산은 피할 수 없었어. 뚜렷한 목표도 엄격한 규율도 없는 용병단이 황야에서 살아남기란 매우 힘든 일이었으니까. 아마도 로도스 아일랜드 같은 조직만이 이 아름다운 것들을 지켜낼 수 있을지도 몰라. 이곳에 오게 된 건 정말 행운이라고 생각해.",
                "cn": "解散是必然的，没有明确的目标，也没有严格的纪律，佣兵队很难在荒野上生存下去......也许只有像罗德岛这样的组织，才能真正守护一些美好的东西，我很幸运能来到这里。"
            },
            "asset": "char_4063_quartz/CN_009"
        },
        {
            "id": "char_4063_quartz_CN_010",
            "title": {
                "en": "Idle",
                "jp": "放置",
                "kr": "방치",
                "cn": "闲置"
            },
            "text": {
                "en": "Doctor, if you don't need anything from me, I'll idle here a little... Feel free to talk to me anytime you need me.",
                "jp": "ドクター、特に用がないなら少しぼんやりしていようと思うが……何かあればいつでも呼んでくれて構わないよ。",
                "kr": "박사, 시킬 일이 없다면 잠깐 멍하니 있을까 하는데…… 무슨 일 있으면 언제든 불러 줘.",
                "cn": "博士，没什么事儿的话，我发会儿呆......您可以随时叫我。"
            },
            "asset": "char_4063_quartz/CN_010"
        },
        {
            "id": "char_4063_quartz_CN_011",
            "title": {
                "en": "Onboard",
                "jp": "入職会話",
                "kr": "오퍼레이터 입사",
                "cn": "干员报到"
            },
            "text": {
                "en": "Hello, Doctor. I'm Quartz... I think I'm on time.",
                "jp": "はじめてお目にかかります、ドクター。私はクォーツという者で……失礼、この時計通りならば、遅刻はしていないですよね。",
                "kr": "처음 뵙겠습니다, 박사. 전 쿼츠라고 합니다…… 실례지만, 시계 대로라면 지각을 한 건 아니겠군요.",
                "cn": "博士您好，我是石英......我应该没有迟到。"
            },
            "asset": "char_4063_quartz/CN_011"
        },
        {
            "id": "char_4063_quartz_CN_012",
            "title": {
                "en": "Watching Battle Record",
                "jp": "経験値上昇",
                "kr": "작전기록 학습",
                "cn": "观看作战记录"
            },
            "text": {
                "en": "I wish our squad could've fought like this back there.",
                "jp": "私のいた傭兵部隊も、このように戦えていたらな……",
                "kr": "내가 있었던 용병단도 이렇게 싸울 수 있었다면 좋았을 텐데.",
                "cn": "如果当时我们的队伍也能像这样战斗就好了。"
            },
            "asset": "char_4063_quartz/CN_012"
        },
        {
            "id": "char_4063_quartz_CN_013",
            "title": {
                "en": "Promotion 1",
                "jp": "昇進Ⅰ",
                "kr": "1차 정예화 (승진)",
                "cn": "精英化晋升1"
            },
            "text": {
                "en": "Thanks for your recognition, but remember to tell me if there's anything I can improve on.",
                "jp": "認めてくれてとても嬉しく思う。もし何か足りないところがあれば、遠慮せず言ってほしい。",
                "kr": "인정해 줘서 고마워. 혹시 내게 부족한 부분이 있다면, 바로 얘기해 줬으면 좋겠어.",
                "cn": "非常感谢您的肯定，如果我有什么做得不好的地方，也请告诉我。"
            },
            "asset": "char_4063_quartz/CN_013"
        },
        {
            "id": "char_4063_quartz_CN_014",
            "title": {
                "en": "Promotion 2",
                "jp": "昇進Ⅱ",
                "kr": "2차 정예화 (승진)",
                "cn": "精英化晋升2"
            },
            "text": {
                "en": "Rhodes Island's promotion process and standards are pretty transparent. That's not easy to do.",
                "jp": "ロドスの昇進は過程も基準も透明性が高い。なかなかできることではないよ。",
                "kr": "로도스 아일랜드의 승진은 기준과 과정이 모두 투명해. 이건 쉽게 할 수 있는 일은 아니지.",
                "cn": "罗德岛的晋升过程和标准都很透明，能做到这点真不容易。"
            },
            "asset": "char_4063_quartz/CN_014"
        },
        {
            "id": "char_4063_quartz_CN_017",
            "title": {
                "en": "Added to Squad",
                "jp": "編成",
                "kr": "팀 배치",
                "cn": "编入队伍"
            },
            "text": {
                "en": "Hope I can help.",
                "jp": "お役に立てれば。",
                "kr": "내가 도움이 됐으면 좋겠네.",
                "cn": "希望我能帮得上忙。"
            },
            "asset": "char_4063_quartz/CN_017"
        },
        {
            "id": "char_4063_quartz_CN_018",
            "title": {
                "en": "Appointed as Squad Leader",
                "jp": "隊長任命",
                "kr": "팀장 임명",
                "cn": "任命队长"
            },
            "text": {
                "en": "Don't worry. I think my decisions through.",
                "jp": "心配はいらない。判断は慎重に行う。",
                "kr": "안심해, 신중하게 판단할 테니까.",
                "cn": "请您放心，我会谨慎地做决定的。"
            },
            "asset": "char_4063_quartz/CN_018"
        },
        {
            "id": "char_4063_quartz_CN_019",
            "title": {
                "en": "Depart",
                "jp": "作戦準備",
                "kr": "작전 출발",
                "cn": "行动出发"
            },
            "text": {
                "en": "I propose we begin our operation at the top of the hour. It'll be easier to keep track of time.",
                "jp": "行動開始は正時にすることを提案する。そのほうが時間を把握しやすい。",
                "kr": "정각에 작전을 개시하는 걸 제안한다. 그러는 편이 시간을 파악하기 쉬워.",
                "cn": "我建议行动定在整点开始，这样方便把控时间。"
            },
            "asset": "char_4063_quartz/CN_019"
        },
        {
            "id": "char_4063_quartz_CN_020",
            "title": {
                "en": "Begin Operation",
                "jp": "戦闘開始",
                "kr": "작전 개시",
                "cn": "行动开始"
            },
            "text": {
                "en": "Hide, and make sure to put out the cooking fire.",
                "jp": "さあ、各自に隠れて。炊事用の焚き火もしっかり消しておくように。",
                "kr": "자, 다들 숨어. 취사용 모닥불 끄는 것도 잊지 말고!",
                "cn": "隐蔽。记得熄灭做饭的火堆！"
            },
            "asset": "char_4063_quartz/CN_020"
        },
        {
            "id": "char_4063_quartz_CN_021",
            "title": {
                "en": "Selecting Operator 1",
                "jp": "選択時1",
                "kr": "오퍼레이터 선택 1",
                "cn": "选中干员1"
            },
            "text": {
                "en": "Doctor, I'm in position.",
                "jp": "位置についたぞ、ドクター。",
                "kr": "위치에 도착했다, 박사.",
                "cn": "我就位了，博士。"
            },
            "asset": "char_4063_quartz/CN_021"
        },
        {
            "id": "char_4063_quartz_CN_022",
            "title": {
                "en": "Selecting Operator 2",
                "jp": "選択時2",
                "kr": "오퍼레이터 선택 2",
                "cn": "选中干员2"
            },
            "text": {
                "en": "You need me to put away my weapon for the time being? Then my sword...",
                "jp": "ここは一旦武器を収めた方がいいか？しかし私の剣は……",
                "kr": "일단 무기를 거둬야 하나? 하지만 내 검은……",
                "cn": "需要暂时收起自己的武器吗？那我的剑......"
            },
            "asset": "char_4063_quartz/CN_022"
        },
        {
            "id": "char_4063_quartz_CN_023",
            "title": {
                "en": "Deployment 1",
                "jp": "配置1",
                "kr": "배치 1",
                "cn": "部署1"
            },
            "text": {
                "en": "Perfect timing!",
                "jp": "時間通りだ。",
                "kr": "시간을 딱 맞췄군.",
                "cn": "时间刚刚好！"
            },
            "asset": "char_4063_quartz/CN_023"
        },
        {
            "id": "char_4063_quartz_CN_024",
            "title": {
                "en": "Deployment 2",
                "jp": "配置2",
                "kr": "배치 2",
                "cn": "部署2"
            },
            "text": {
                "en": "A bit slow, but hardly a big problem.",
                "jp": "少しだけ遅れた。だが問題はない。",
                "kr": "조금 늦었지만 문제없다.",
                "cn": "慢了一些，但是问题不大。"
            },
            "asset": "char_4063_quartz/CN_024"
        },
        {
            "id": "char_4063_quartz_CN_025",
            "title": {
                "en": "In Battle 1",
                "jp": "作戦中1",
                "kr": "작전 중 1",
                "cn": "作战中1"
            },
            "text": {
                "en": "Timing your strikes is more important than brute strength.",
                "jp": "力よりも、攻撃のタイミングが重要だ。",
                "kr": "힘보다는 타이밍이 더 중요하다.",
                "cn": "比起力道，重要的是出剑的时机。"
            },
            "asset": "char_4063_quartz/CN_025"
        },
        {
            "id": "char_4063_quartz_CN_026",
            "title": {
                "en": "In Battle 2",
                "jp": "作戦中2",
                "kr": "작전 중 2",
                "cn": "作战中2"
            },
            "text": {
                "en": "Keep your distance. You could get hurt.",
                "jp": "私に近付きすぎないでくれ。味方を誤って傷つけたくない。",
                "kr": "다칠 수도 있으니까, 너무 가까이 오지는 마.",
                "cn": "和我保持距离，小心被误伤。"
            },
            "asset": "char_4063_quartz/CN_026"
        },
        {
            "id": "char_4063_quartz_CN_027",
            "title": {
                "en": "In Battle 3",
                "jp": "作戦中3",
                "kr": "작전 중 3",
                "cn": "作战中3"
            },
            "text": {
                "en": "When you stare at my eyepatch, it reveals a lot.",
                "jp": "この眼帯に気を取られているようでは、逆に見透かされるぞ。",
                "kr": "이 안대에 정신이 팔렸다간, 오히려 간파당하고 말 걸.",
                "cn": "盯着我的眼罩看，会暴露很多东西的。"
            },
            "asset": "char_4063_quartz/CN_027"
        },
        {
            "id": "char_4063_quartz_CN_028",
            "title": {
                "en": "In Battle 4",
                "jp": "作戦中4",
                "kr": "작전 중 4",
                "cn": "作战中4"
            },
            "text": {
                "en": "Take this!",
                "jp": "この一撃で決める！",
                "kr": "이 일격으로 끝낸다!",
                "cn": "就这一击！"
            },
            "asset": "char_4063_quartz/CN_028"
        },
        {
            "id": "char_4063_quartz_CN_029",
            "title": {
                "en": "4-star Result",
                "jp": "高難度作戦クリア",
                "kr": "고난이도 작전 종료",
                "cn": "完成高难行动"
            },
            "text": {
                "en": "Victory is assured when every phase of the mission proceeds with watchlike precision.",
                "jp": "時計の針のように正確な作戦遂行ができれば、勝利は自ずと訪れるものだ。",
                "kr": "시곗바늘처럼 정확한 작전 수행을 할 수 있다면, 승리는 저절로 따라오기 마련이야.",
                "cn": "每个环节都像指针转动般精确，那胜利自然会准时到来。"
            },
            "asset": "char_4063_quartz/CN_029"
        },
        {
            "id": "char_4063_quartz_CN_030",
            "title": {
                "en": "3-star Result",
                "jp": "★3で戦闘終了",
                "kr": "3★ 작전 종료",
                "cn": "3星结束行动"
            },
            "text": {
                "en": "This is worth celebrating... When we get back to Rhodes Island, we won't have to eat my cooking anymore.",
                "jp": "祝うべき勝利だ……ロドスへ帰還したら、皆ももう私の料理など食べずに済むしな。",
                "kr": "축하할 만한 승리야…… 로도스 아일랜드에 돌아갈 테니, 다들 내가 만든 요리를 더 이상 먹지 않아도 되겠어.",
                "cn": "值得庆祝......回到罗德岛后，大家就可以不用吃我做的饭了。"
            },
            "asset": "char_4063_quartz/CN_030"
        },
        {
            "id": "char_4063_quartz_CN_031",
            "title": {
                "en": "Sub 3-star Result",
                "jp": "★2以下戦闘終了",
                "kr": "비 3★ 작전 종료",
                "cn": "非3星结束行动"
            },
            "text": {
                "en": "Even the most accurate of watches isn't always accurate. Don't be so fixated on perfection",
                "jp": "いくら精密な時計でも、時には狂うこともある。そこまで完璧さに拘ることもないよ、ドクター。",
                "kr": "아무리 정밀한 시계라도 가끔은 어긋나기도 하지. 그러니까 너무 완벽함에 연연할 필요 없어, 박사.",
                "cn": "再精密的钟表偶尔也会有失准的时候，您不必太苛求完美。"
            },
            "asset": "char_4063_quartz/CN_031"
        },
        {
            "id": "char_4063_quartz_CN_032",
            "title": {
                "en": "Operation Failure",
                "jp": "作戦失敗",
                "kr": "작전 실패",
                "cn": "行动失败"
            },
            "text": {
                "en": "Sorry, Doctor, we had a few problems with the plan because my watch is broken. Go on ahead and leave the rest to me.",
                "jp": "すまない、ドクター、私の時計が壊れたようだ。作戦の段取りにおいてミスをしてしまった……後始末は私に任せて、先に行ってくれ。",
                "kr": "미안해, 박사. 시계가 고장 나서 작전 순서에 문제가 생긴 것 같아. 뒤처리는 나한테 맡기고 먼저 가.",
                "cn": "抱歉，博士，我的表坏了，安排上出了一些问题。您先走，后面的事情交给我。"
            },
            "asset": "char_4063_quartz/CN_032"
        },
        {
            "id": "char_4063_quartz_CN_033",
            "title": {
                "en": "Assigned to Facility",
                "jp": "基地配属",
                "kr": "시설에 배치",
                "cn": "进驻设施"
            },
            "text": {
                "en": "This is much more comfortable than a tent in the wilderness... Will someone stand watch at night?",
                "jp": "荒野のテント暮らしよりは全然快適だ……誰かが夜番しなくていいのか？",
                "kr": "황야 위의 텐트보다는 훨씬 쾌적하네…… 누군가가 불침번을 설 필요는 없는 건가?",
                "cn": "这里比荒野上的帐篷可舒适多了......会安排人守夜吗？"
            },
            "asset": "char_4063_quartz/CN_033"
        },
        {
            "id": "char_4063_quartz_CN_034",
            "title": {
                "en": "Tap",
                "jp": "タッチ1",
                "kr": "터치",
                "cn": "戳一下"
            },
            "text": {
                "en": "Oh, Doctor. What's the matter?",
                "jp": "ん？ドクターか、どうした？",
                "kr": "어, 박사, 무슨 일이지?",
                "cn": "啊，是博士，怎么了？"
            },
            "asset": "char_4063_quartz/CN_034"
        },
        {
            "id": "char_4063_quartz_CN_036",
            "title": {
                "en": "Trust Tap",
                "jp": "信頼タッチ",
                "kr": "신뢰도 터치",
                "cn": "信赖触摸"
            },
            "text": {
                "en": "Let's space out together, Doctor. We can chill for as long as we need... It's all in the past.",
                "jp": "一緒に一息つくか、ドクター――ぼうっとするのに時間を気にする必要はない……あれはもう、遠い昔のことだ。",
                "kr": "같이 한숨 돌리자, 박사. 멍때리는 데 시간제한 같은 건 없어…… 그런 건 이미, 오래전 일이 됐으니까 말이야.",
                "cn": "一起发会呆吧，博士。发呆当然没有时间限制......那已经是很早以前的事情了。"
            },
            "asset": "char_4063_quartz/CN_036"
        },
        {
            "id": "char_4063_quartz_CN_037",
            "title": {
                "en": "Title",
                "jp": "タイトルコール",
                "kr": "타이틀",
                "cn": "标题"
            },
            "text": {
                "en": "Arknights.",
                "jp": "アークナイツ。",
                "kr": "명일방주.",
                "cn": "明日方舟。"
            },
            "asset": "char_4063_quartz/CN_037"
        },
        {
            "id": "char_4063_quartz_CN_042",
            "title": {
                "en": "Greeting",
                "jp": "挨拶",
                "kr": "인사",
                "cn": "问候"
            },
            "text": {
                "en": "Hello, Doctor. Careful. You almost bumped into my sword.",
                "jp": "こんにちは、ドクター。気をつけて。危うく私の剣にぶつかるところだったぞ。",
                "kr": "안녕, 박사. 조심해, 하마터면 내 검에 부딪힐 뻔했잖아.",
                "cn": "博士您好。小心，您差点撞在我的剑上了。"
            },
            "asset": "char_4063_quartz/CN_042"
        }
    ],
    "actors": {
        "cn": {
            "native": "虫虫",
            "global": "Jen Zhang"
        },
        "jp": {
            "native": "逢田梨香子",
            "global": "Rikako Aida"
        },
        "kr": {
            "native": "김윤채",
            "global": "Kim Yun-chae"
        }
    },
    "availability": [
        "cn",
        "jp",
        "kr"
    ]
}